{"id": "doc_zst_2024_guojiu", "date": "2024-04-03", "title": "开启十年新周期的国九条", "summary": "新国九条:资本市场改革;十年新周期", "core_claim": "", "snippet": "", "source_url": "", "content": "# 开启十年新周期的《国九条》\n\n今天，市场期待已久的第三版《国九条》终于出来了，\n\n新华社官宣，国务院近日印发《关于加强监管防范风险推动资本市场高质量发展的若干意见》。\n\n这是继2004年、2014年两个“国九条”之后，国务院再次出台的资本市场指导性文件，本次也很默契的把意见再次归结为“九条”。\n\n这是一个非常重磅的信号，\n\n每次国务院出台该文件，都标志着国家未来十年的经济发展路线确定，资本市场要择机重启融资的功能。\n\n隐藏内容需要支付：&yen;6.6\n\n立即购买\n\n查看隐藏内容需要支付：\n\n&yen;6.6\n\n微信支付\n\n立即支付\n\n请使用\n微信支付                扫码支付", "content_source": "corpus_md", "content_chars": 301, "fq": "A", "il": ""}