{"id": "doc_zst_0013", "date": "2016-02-21", "title": "中国贫富差距大的原因很大程度上是户籍制度吗？", "summary": "中国贫富差距大的原因很大程度上是户籍制度吗？", "core_claim": "", "snippet": "中国贫富差距大的原因很大程度上是户籍制度吗？ 【20160221A01】 是的。但是这事儿不宜讨论。 太祖66年联合周公发动WG，搞掉了刘哀公的走资派；67年二月逆流，联合林 二哥搞掉了周公的保守派。 68年，斗倒了所有的政治对手之后，太祖爷就放开手为自己的政治理想进行实 践，那就是——“上山下乡”！ 所以嘛，WG与“上山下乡”相比，哪个是手段，哪个是目的，这是一个有趣 的话题。 再后来，大哥的亲密战友二哥71年挂了，太祖又回到了65年之前的三足鼎立时 代，被联手遏制丧失话语权。 所以上山下乡自然也就终结了。周公马上跟叶帅组织走后门就把子弟们都接回 来了。 就像血色浪漫里面的知识青年李援朝和张海洋，换上皮就成了红二代，甚至当 年在陕北一床被子住窑洞啃窝窝头的哥俩 如今变成了董事局的哒哒和隔壁", "source_url": "", "content": "中国贫富差距大的原因很大程度上是户籍制度吗？ \n\n【20160221A01】 \n\n是的。但是这事儿不宜讨论。 \n\n太祖66年联合周公发动WG，搞掉了刘哀公的走资派；67年二月逆流，联合林\n二哥搞掉了周公的保守派。 \n\n68年，斗倒了所有的政治对手之后，太祖爷就放开手为自己的政治理想进行实\n践，那就是——“上山下乡”！ \n\n所以嘛，WG与“上山下乡”相比，哪个是手段，哪个是目的，这是一个有趣\n的话题。 \n\n再后来，大哥的亲密战友二哥71年挂了，太祖又回到了65年之前的三足鼎立时\n代，被联手遏制丧失话语权。 \n\n所以上山下乡自然也就终结了。周公马上跟叶帅组织走后门就把子弟们都接回\n来了。 \n\n就像血色浪漫里面的知识青年李援朝和张海洋，换上皮就成了红二代，甚至当\n年在陕北一床被子住窑洞啃窝窝头的哥俩 如今变成了董事局的哒哒和隔壁叔\n叔。只是当年蹲监狱的如今还在蹲监狱。 \n\n上山下乡的最本质目的，难道不就是妄图改变城市剥削农村，打破户籍制度，\n想消除城乡差距么？ \n\n但是这么做将损害所有城市里既得利益者的利益，包括绝大部分党的高级干部，\n所以失败不可避免。太祖为啥众叛亲离，还不是自己zuo得么。 \n\n城里人想要活得好，就必然会通过剥削农村来实现，户籍制度就是保障，至于\n\n如何做到，其他回答里必然会有，我也懒得码字了。 \n\n想要改变这个情况， 太祖的路是行不通的。 我支持@牢不萌的观点 （顺带谢邀） ，\n只能靠生产力与生产关系的前进，当农村不再是peasant，而是farmer时，才\n会改变，而这个想实现，就得继续推动工业化和产业升级。 \n\n但是过程中，这种剥削与门槛会存在很久，譬如说，今年房地产泡沫、经济硬\n着陆这个锅，现在不就是让想跨过这道门槛的农民兄弟们去背么？", "content_source": "pdf_split", "content_chars": 741, "fq": "A", "il": ""}