{"id": "doc_zst_0402", "date": "2017-05-08", "title": "今日，法国祁同伟当选总统，中国人民迎来老朋友", "summary": "今日，法国祁同伟当选总统，中国人民迎来老朋友", "core_claim": "", "snippet": "今日，法国祁同伟当选总统，中国人民迎来老朋友 【20170508A01】 他是一个从农村出来的优秀青年，他有着一张英俊的面容，上学时候就和她的 老师有暧昧，毕业后在社会碰了壁之后，回头拼命追求自己的老师。而这位背 景雄厚的老师，最终选择了跟他在一起，凭借她的资源，使得他年纪轻轻就身 居高位。 嗯，政事堂说的不是热剧《人民的名义》中的祁同伟和梁璐，而是法国新任总 统马克龙和他夫人。 不过这马克龙可比祁同伟牛逼多了，老婆布丽吉特比自己大24岁，而且他跟他 夫人结婚的时候，他的夫人已经有了三个子女和 7个孙子辈的了。（手动脑补 一树梨花压海棠） 而今早，法国大选结果出来，马克龙高票战胜极右翼的勒庞，当选法国新任总 统，将与妻子牵手入主爱丽舍宫。 从一介屌丝，成为如今全球最有权力的人之一，马克龙只用", "source_url": "", "content": "今日，法国祁同伟当选总统，中国人民迎来老朋友 \n\n【20170508A01】 \n\n他是一个从农村出来的优秀青年，他有着一张英俊的面容，上学时候就和她的\n老师有暧昧，毕业后在社会碰了壁之后，回头拼命追求自己的老师。而这位背\n景雄厚的老师，最终选择了跟他在一起，凭借她的资源，使得他年纪轻轻就身\n居高位。 \n\n嗯，政事堂说的不是热剧《人民的名义》中的祁同伟和梁璐，而是法国新任总\n统马克龙和他夫人。\n\n不过这马克龙可比祁同伟牛逼多了，老婆布丽吉特比自己大24岁，而且他跟他\n夫人结婚的时候，他的夫人已经有了三个子女和 7个孙子辈的了。（手动脑补\n一树梨花压海棠） \n\n而今早，法国大选结果出来，马克龙高票战胜极右翼的勒庞，当选法国新任总\n统，将与妻子牵手入主爱丽舍宫。 \n\n从一介屌丝，成为如今全球最有权力的人之一，马克龙只用了十年。 \n\n2007年布丽吉特因马克龙离婚，而马克龙也从这一年，开启了他的飞黄腾达之\n旅。 \n\n婚后的马克龙，成为了当代最有影响力的经济学者阿塔利的闭门子弟，在这位\n法国总统经济顾问、欧洲复兴开发银行创建者的支持下，30岁的马克龙成为了\n“提高法国经济增长特别委员会”的副报告人，其地位，相当于我国的中财办\n副主任。 \n\n不过2008年的欧债危机， 使得这位政治新星黯然失色， 委员会的改革方案失败，\n法国经济陷入泥潭。不过，这难不倒马克龙，在看不见的手的运作下，马克隆\n\n成为了一名罗斯柴尔德银的银行家， 而这位刚入行， 还在学习Excel的实习生，\n随即成为了负责雀巢和辉瑞这两家顶级巨头之间，90亿欧元巨额交易的合伙人。 \n\n2010年，完善了金融履历的马克龙，被推荐到了奥朗德身边成为亲随。 2012\n年，随着奥朗德就职法国总统，作为从龙之臣，马克龙被任命为总统的副秘书\n长。嗯，马克龙的背景，估计他用不着哭坟。 \n\n2014年8月，法国政府改组，时年36岁的马克龙，在他老师的强力推荐下，出\n任法国经济、工业和数字经济部长，成为共和国最年轻的部长。 \n\n而此次马克龙当选总统，更是成为了法兰西有史以来最年轻的总统。 \n\n当然此次最高兴的，莫过于欧盟的小伙伴们，因为马克龙的竞争对手勒庞一直\n宣称要退出欧盟，而英法德一直是欧盟的“三驾马车”，在英国脱欧之后，脆\n弱的欧盟已经岌岌可危。 \n\n要知道，马克龙的老师阿塔利，可是欧盟的主要推动人和条约起草人之一，所\n以嘛，德国总理默克尔第一时间给马克龙打电话，表达了衷心祝贺。 \n\n相信这个时候，马克龙的老师阿塔利也会推一推眼镜，微微一笑，心中默想，\n老子的汉大帮，啊，不对，老子的欧盟总算没垮。 \n\n而马克龙的当选，也使得政事堂在去年，预测五大流氓保守派集体上台，成为\n了泡影。\n\n当然，这对咱们国家是好事儿，要知道，马克龙的竞争对手勒庞，可是拜过靖\n国神社的家伙。 \n\n而且如今这位法国的新总统，对中国非常善意，其担任法国经济部长期间力挺\n中国收购法国图卢兹机场的交易，而今年 3月，旅法华人刘少尧在巴黎家中被\n警察射杀后，马克龙也是唯一会见了死者家属与巴黎华侨代表的总统候选人。 \n\n而且，马克龙很喜欢引用中国领导人的名言。 \n\n据报道，马克龙在接受该报采访时自称是“毛派”。他解释说，因为对毛泽东\n来说，“能奏效的方案就是好方案”，它代表的是一种高效的行动力。在三月\n竞选活动、分析民调最为紧张的时刻，他和团队成员将其比作“长征”。 \n\n后来在采访时，马克龙又引用了邓小平的名言，“不管黑猫白猫，抓到老鼠就\n是好猫”。 \n\n当然，马克龙这种所谓的，超越左右党派的政治理念，一度被法国民众，揶揄\n为法国著名甜点“马卡龙”——外表光鲜，内在绵软。\n\n当然，这位法国大资本家的代言人上台之后，什么人会过上甜日子，大家心里\n应该都明白。 \n\n写到马卡龙，突然饿了。政事堂写不下去了。我们明晚再见！ \n\n真的首富往往是藏匿极深，不愿意让别人知道你是谁，譬如马克龙的夫人，你\n们根本找不到她的任何信息。反之，越是缺钱，就越需要彰显自己有钱，譬如\n说，现在每天都在炫富的郭某。", "content_source": "pdf_split", "content_chars": 1673, "fq": "A", "il": ""}