{"id": "doc_zst_2025_trump_copy_cn", "date": "2025-05-28", "title": "特朗普：抄袭兔子的改革路", "summary": "特朗普改革=抄袭中国:DOGE=中纪委;关税=供给侧改革;金卡=招商引资;中东行=一带一路;产业政策=五年计划;=换房本的中国经验美国翻版", "core_claim": "", "snippet": "", "source_url": "", "content": "RHE: 抄效兔子的改革路 发布时间 : 2025 年 5 月 28 日 2025 年特朗普针对美国私立大学的招生限制 , 可 以参考 2022\n年东大对私人教培机构的招生限制。 2025 年特朗 普针对美国医保用药 的价格屠刀 可以参考 2022\n年东大对医保用药的价格屠刀。 2025 年特 朗普 动针对美国政府机构 大幅削减经费 , 可以参考 2022 年东大打压公务 员\n、类企和金融机 构 的薪资。 可以 说 , 几乎所有特朗普令人惊诺的行为 , 都会 在 2022 年的东大 ,\n找到对应的动作。甚至在这种 “ 频 折腾 ”之 下 , 近期好多国家都启动了迎接 “ 美润四 方 ”的 准备 ,\n进提升 知识学习群 , 看更多优质 资源\n而这些令 外人费解的动作 , 在美国国内 却 又能得到足够多的支持 , 正如 2025 年美国人自豪的打出了 “” 也可以参考 2022\n年东大民众微信头像右下角 的 “ “” 没有本质上的区 别 ,《〈 图案看截图 ) 正如 2025 年美国人自豪 的打出了号加起 也\n可以参考 2022 年东大民众微信头像右下角 a , ‘onda SM yaam ines, 中美都是受疫情冲击 , 导致财政亏空 最重的国家 ,\n执政集团都需要通过海外掠夺 , 来转移国内矛盾也都 准备借助债务压力 , 推动内部的 一系列改革 ,\n进提升 知识学习群 , 看 更多优质 资源\n特朗普的改革若是能够相对顺畅 , 那么美国很多经 济 模型, 都 可 以从先行改革的东大找到借鉴 的意义 , 回顾 2022 年 ,A 股\n、A 房 、A 债 、利 率、通 胀 , 似乎 都从最高点开启了持续数年的单 边的下跌。 FE tH Wz 美国政府 Signal 群组泄露事件 8\n来源 : 维基百科 8 LD 4 FRE SERA A, WIE + KIRK (Michae Waltz ,美国 国家安全事务助理 ) 向 JD 万 斯 (James David\nVance, SEX EB RA) IT 202543A ORE un ae 册 as 也门的结果。 , 进提升知识学习 群 , 看更多优质资源\n提升知识学习群 365 一 年 (365 天服务期 ) , 微信质资源 , 老客户\n进群享折扣。学习群包含以下全部资源 : 一、财经类博主 : om MADR (RR um) OFee eC 和也 全 对 2 1、 子明私享汇 (原价\n568 元 /年 ) / 单买 29. 9 一年 ne 2、 米糕米联储 见闻〈原价 599 元/ 年) / 单买 29. 9 一年 Obes 3、 大树乡\n谈知识星球〈原价 199 元 /年 ) / 单买 19.9 一年 4、 猫哥的世界知识星球 (原价 299 元/ 年) / 单 买 19.9- 年 ass 码 添、 砖瓦厂赵阿 9 的内部文章 (原价 400 元 /年 ) / 单买 19.9 一年 扫 取 直 - oo 免费领取资料 6、 卢克文知识星球 :青云\n会会员文章 原价 268 元 /年 ) 单买 9.9 一年 ! 免费 试读体验 1?、 卢克文青云读书会 (原价 699 元 /年 ) / 单买 59.9 一年 满意\n再进群 , 8、 谷宗供会员群文章和对话 (原价 365 元 /年 ) / 单买 29.9 一年 更 新 365 天 , 送历史文章 ! 9、\n欧洲金靴会员群文章 (原价 328 元 /年 ) / 单买 19. 9 一年 Ure cies cect 一- 10、 眉树西风公众 号付费文章 , 单买 29. 9 一年\n11、 江宁知府公众号付费 文章 , 单买 29. 9 一年 三、各种公众号付费文 : 洪涉的宏观策略、金政通\n鉴、局外人的视界、涉泽异 谈、雪球花甲老头、幻约话你知、 NEO 摸鱼录、冷眼局中人、 观海谈五行对股市\n的影响、费曼的小茶馆、赢 在八小时之外、 A 视 野、雷思 海、盛 京剑客、第 三章眼观等 等公众号付费文章 不定时更 新 ,\n内容不 一一列举 进提升知识学习 群包含以上全部内容 , 分享 365 天 , 赠送历史文章 ! , 进提升\n知识学习群 , 看更多优质 资源", "content_source": "yearly_pdf", "content_chars": 1758, "fq": "A", "il": ""}