{"id": "doc_zst_0016", "date": "2016-02-27", "title": "如何看待「大炮」任志强遭官媒猛烈炮轰？", "summary": "如何看待「大炮」任志强遭官媒猛烈炮轰？", "core_claim": "", "snippet": "如何看待「大炮」任志强遭官媒猛烈炮轰？ 【20160227A01】 先说党媒姓党，对不对？当然对！ 但是这句话是什么？是政治规矩！ 近年来，陛下批评过很多人不守政治规矩，但是从来不明确说政治规矩都有什 么。 这当然不算不教而诛。 政治像下棋一样，规矩是给场上玩家准备的，而不是告诉棋子的。 棋子嘛，是用来交换的、抛弃的、用来最终获取胜利的。 再说把党媒姓党放出来这事儿。 有句俗话，爱不是说出来的，是做出来的。 党媒真要姓党就别整天妄议中央。 陛下为啥去视察一台两社之前说过，文官对抗陛下的最佳方式就是捧杀，陛下 本次就是要去帮黄侍郎站队固权。 固权的目的嘛，就像如今媒体们这么高调宣扬本次视察的“党媒姓党”，并不 是陛下钦点的标题“党与人民同呼吸”。不固权行么？ 否则从今年开始的三年经济自然灾害，", "source_url": "", "content": "如何看待「大炮」任志强遭官媒猛烈炮轰？ \n\n【20160227A01】 \n\n先说党媒姓党，对不对？当然对！ \n\n但是这句话是什么？是政治规矩！ \n\n近年来，陛下批评过很多人不守政治规矩，但是从来不明确说政治规矩都有什\n么。 \n\n这当然不算不教而诛。 \n\n政治像下棋一样，规矩是给场上玩家准备的，而不是告诉棋子的。 \n\n棋子嘛，是用来交换的、抛弃的、用来最终获取胜利的。 \n\n再说把党媒姓党放出来这事儿。 \n\n有句俗话，爱不是说出来的，是做出来的。 \n\n党媒真要姓党就别整天妄议中央。 \n\n陛下为啥去视察一台两社之前说过，文官对抗陛下的最佳方式就是捧杀，陛下\n本次就是要去帮黄侍郎站队固权。 \n\n固权的目的嘛，就像如今媒体们这么高调宣扬本次视察的“党媒姓党”，并不\n是陛下钦点的标题“党与人民同呼吸”。不固权行么？ \n\n否则从今年开始的三年经济自然灾害， 就像当年大跃进x万亿的锅， 是由当年实\n际的推动者来背？还是由如今英明神武的领袖来背呢？\n\n再说任志强，这丫的后台属于公开信息了，铁杆保守党成员。所以嘛，别以为\n他这么放炮是攻击陛下，看看反击大炮的几乎是一色团媒和地方媒，却没有党\n媒就知道了。大炮这次可是标准的站在“人民”的角度说话，而最近陛下已经\n命令党员重新开始学习毛泽东思想了，毛泽东思想的核心可就是为人民服务 。\n所以嘛，别以为大炮是政治傻逼，他溜着呢。 \n\n最后再夹点私货，这事儿让我想起一个成语，指鹿为马。 \n\n这个马主义嘛，完全看怎么说， \n\n赵家人高，这么一搞，那些还说鹿的话筒子，没多久就都跪了。 \n\n另外，李丞相斯，也跪了。 \n\n按照姬大喵的说法，没多久，咱大秦，也跪了。 \n\n妈蛋的，按地域和辈分来算，陛下的确算是秦二世了。", "content_source": "pdf_split", "content_chars": 726, "fq": "A", "il": ""}