{"id": "doc_zst_2025_iran_israel_3", "date": "2025-06-02", "title": "伊以冲突的三个关键时间点", "summary": "伊以冲突预判:6/13以色列空袭伊朗核设施(纳坦兹/福尔道)→炸死总参谋长巴盖里+革命卫队司令萨拉米+多名核科学家;伊朗6/13夜发射150+枚弹道导弹反击;6/24停火;三个关键时间点=作者提前预判", "core_claim": "", "snippet": "", "source_url": "", "content": "# 伊以冲突的三个关键时间点\n\n《战争论》说，战争是政治的延续。\n\n如果从一个政治爱好者的角度来看伊以这场军事冲突，以色列成功的三大个关键时间点是：\n\n1、24年7月，拜登癌症被发现\n\n2、24年7月，特朗普枪击案\n\n3、24年11月，共和党赢得总统、两院\n\n看似毫无关联，但还缺一不可。\n\n1、因为拜登癌症，不得不退选，民主党陷入内部权利争斗，无心压制内塔尼亚胡，使得以色列可以在24年下半年强行出手，消灭了哈马斯与真主党等以色列外围力量的首脑，空袭掉大量的伊朗防空力量。\n\n2、因为枪击案，特朗普如有神助胜率大增，泛特朗普阵营之间，开始相互密切交易，内塔尼亚胡、埃尔多安和普京一顿交易后，出卖了叙利亚，为以色列打开了空袭通道。内塔尼亚胡与小萨勒曼、埃尔多安迅速合作，让全球的逊尼派抛弃了什叶派教友；俄罗斯等安理会常跟美国唱反调的国家也默许以色列的特别军事行动。\n\n3、因为共和党同时拿下白宫与国会山，使得特朗普可以绕过国会的授权，直接支持以色列发动战争，并得到美国国家力量和五角大楼的大力支持，清缴胡赛武装，准备B2轰炸机等事宜。\n\n罗列这些，并不是说以色列靠的是运气和别人的帮助，而是佩服犹太人的严谨与精密，以色列突袭伊朗的窗口期非常之短，有三条钢丝一般的时间线，必须严格卡着：\n\n1、以色列的军事与外交行动，必须晚于24年7月，也就是拜登退选、特朗普枪击后。\n\n2、以色列动用美国的军事与外交力量必须晚于25年1月，也就是特朗普团队上台后。\n\n3、战争必须在25年7月之前开启并迅速结束，也就是库里拉（中央战区司令）退休前。\n\n上帝只给了以色列半年的时间，来搞定美国十年都没搞定的阿萨德政权，也只给了他们半年的时间，制造巨大筹码与安理会大国们做BigDeal以获取他们的绥靖，犹太人也正面刚赢了副总统万斯，逼着战略收缩的美国下场重创胡赛，更在支持以色列的中央战区司令退休前，把需要美军配合的一切都搞定……\n\n这一系列操纵超级大国的“不可能完成的任务”，竟都被他们完成了……不由得惊出一身冷汗。\n\n最近聊犹太人发动的这场战争比较多，是因为他们本轮所做的实践，从安全到外交，从军事战到舆论战，都是我们可以学习借鉴的对象，也许终有一天需要用到。\n\n但更重要的是要警惕和研究我们的对手，此战之顺利，以及回顾24年犹太力量为协助特朗普上台做的一系列动作，表明了犹太势力才是这一轮美国内部政治斗争的胜利者。\n\n也就是说，接下来的四年，附着于特朗普身上的犹太力量也会是跟我们博弈的棋手。\n\n【政事堂】推荐:顾子明的付费知识社群\n\n顾子明，是一位资深的财经分析师，曾在多家知名媒体担任专栏作者。他的分析深入浅出，深受读者喜爱。\n\n现在，顾子明开设了付费识社群，提供更深入的经济分析和投资建议。社群内每周更新多篇深度分析文章，涵盖宏观经济、行业分析、投资策略等方面，让你更好地了解市场动态，把握投资机会。\n\n社群会员还可以参与顾子明的投资组合，跟随他的投资策略，获得更高的收益。同时，社群内还有专业的投资交流群，可以与其他会员交流心得，共同学习成长。\n\n欢迎咨询V：knn5318\n\n读者朋友们，赶快加入顾子明的付费知识社群，开启你的投资之旅。\n\n认知改变命运！整日忙碌，不如提高认知，学习房产、教育和销售、营销实现等赚钱路径，实现家庭升阶！\n\n2025年欢迎您的加入，我们一起去认识世界，一起去探寻自身从未踏足过的目光跟思想局限.", "content_source": "corpus_md", "content_chars": 1411, "fq": "A", "il": ""}