{"id": "doc_zst_2025_us_ru_impact2", "date": "2025-08-20", "title": "警惕新一轮的GS战、镁饿会谈的影响（下）", "summary": "警惕新一轮GS战、镁饿会谈影响(下):美俄会谈后关税战风险;双普情同手足→西欧成了衣服(刘关张兄弟如手足老婆如衣服);俄乌双方顿巴斯日均2000吨弹药→远未达让步临界点;尽管无力量还希望战争持续→但停火仍困难", "core_claim": "", "snippet": "", "source_url": "", "content": "警惕特朗 善新一轮的关税战 发 布时间 : 2025 年 8 月 20 日 Ay HE Tel RO PRA RA Ee, 并大幅取消加征的关税 ,\n既有兔子强硬迫使美国让步的因素 , 现在看来也有特朗普 想在暑假 期间优 先解决俄乌 的原因 , 美国需要兔子在 俄\n鸟问题上的配合 , 就不敢在贸易上对兔子施加过多的压力 , 同样的情况还有特朗普需要拉拢的欧盟 , 声势浩大的贸易谈判 在\n七巨头访问白宫前 就已经 冷 了下来。\n也正 是因为 特 朗 普 出乎市场预料的 TACO0, 全球资本市场迎来了一个火热的夏天。 如 今 , 随着特 朗 普基本殴 定了俄罗斯\n与乌克兰领 导人的会面 , 美国就没必要再看中欧的脸色 , 那么刚刚降温 的关税战就必然要重新加码 虽然全面关税已经结束 ,\n但全球将迎来新一轮特种关税的打击 , 短期内资本市场很可能也将面对新一轮的冲击。 这一轮冲 击不会像全面关税那样震揣 ,\n但涉及的领域将会面临灾难式 的冲击 , 由于钟镁已经达成了不 打半导体和稀土 牌的约定 ,\n估计免子近期主打和反制的手牌会是收获期的大豆 ,\n而美国则可能使用台湾或者南海这种核心利益来 施 压。 延伸阅读 Reuters Trump says no imminent plans to penalize\nChina for buying Russian oil Ae BE AR ST ER th Tl 定惩罚计划 来 源 : 路透社 2025 年 8 月 16 日 8 月 15 日 ,在\n阿拉斯加与普京举行会 晤 后 , 特 朗普 表示 , 暂无针对兔子 等购买俄罗斯石油国家加征关税 的计划。 Oe: “好 吧 ,\n因为今天发生的事情 , 我 想 我 不需要考虑这 个 了 ,”“ 我可能不得 不在两 三周\n后考虑这个问题 , 但我们现在不必考虑这个问题。我 认为会议进行 得很顺利 。” 此 前 , 特朗 普威胁 称 ,\n如果俄罗斯不采取措施结 束鸟克兰战争 , 将对莫斯科实施制裁 , 并对购买俄罗 斯石油国家的输 美商品征收\n次级关税。美国上周以瑟 罚印 度购买俄罗斯石油 为 由 , 宣布对印度商品额外加 征 25% 关税。 泽连斯基就停火问题\n松口俄媒称普京对直接 对话持开放态度 来 源 : 新华网 2025 年 8 月 19 日 泽连斯基表示 , 他已准备好与普京举行 “任何 形\n式 ” 的会 晤 , 会晤不应 该设置任何条 件 。“ 我 无条件 地认为 , 我们应该举行 会晤。 特朗 普当日在社交媒体上发文 说 , 在\n与 泽连斯基 、 欧洲领导人会晤结束之 际 , 他给普京 打了电话 , 并\n已开始安排普京与泽连斯基的双边 会 晤 , 地点待定。 在双边会晤之 后 , 将举行美俄岛三方领导人会晤。 俄罗斯 总 统助理乌\n沙科夫当地时间 19 日凌晨发布 通报 说 , 普 京应约 与特朗普通电话 , 双方表示支持俄 鸟代表团继续进行直接谈判。\n今日俄罗斯通讯社援引克里姆林富 一 名助手的话 报道 说 , 普京对同泽连斯基直接对话的 “想法 ” 持开 BAI. 美国将 407\n类钢铁和馈衍生产品纳入关税清单 来 源 : 央视 新闻 2025 年 8 月 19 日 当地时间 8 月 19 日 , 美国商务部宣布 , 将 407 个产\n品类别纳入钢铁和馈关税清单 , 适用税率为 50%。 | 时见 | 相关内容延展 :\n《美俄会谈的影响 (上 ) 》 来 源 : | 时见 | 知几共话 2025 年 8 月 19 日 之前说这个月要减仓 , 现 在美俄会谈来 了 , 大家\n怎么看接下来的市场形势 ? FU: 看什么涨了赚 大 钱 了就减什么。现在没减 的 只剩券 商了。 还是要到九月初再看看吧。 子明\n: 嗯 , 看局势动 作。美俄会 谈 , 这是在 7 月会 议意料 之外的。 子明 : 我原计划是在阅兵之前基本减到只剩券商 ,\n如果接下来美俄谈得好 话 , 我会加速减仓。 《美俄会谈的影响 (下 ) 》 来 源 : | 时见 | 知几共话 2025 年 8 月 20 晶\nFU: 今天会 后 , 下周开始加速减他了。 没谈出停火也减仓 ? 子明 : 本来就谈不出停火。但是明显双方谈得很 好 了。 子 明 :\n普京说服了特朗 普 , 美 国 的国家战略 ,从 施 压俄罗斯 “停火 ”, 转向施压乌克兰和欧洲 “停战 ” ,\n要求其接受俄罗斯的领土主张。 END 美俄会谈的影响 (下 ) 发布专栏 : 知儿共话 外交 , 没有永远的敌人 , 只有永远 的利益\n2025 年 8 月 16 日 , 欧 盟委员会发言人表示 , 特 朗普 与 泽连斯基及欧洲 多位领导人通了电话 , 讨 论他与普 京的 会喇内容 ,\n该通讯持续了一 个多小 时。 Ber BE AR ATH 18 Wa 4 ti 美 俄会谈结束 后 , 特朗普立 刻 来到欧洲谈判新的 Al it, RAGS\nWAAR. WiK—K, HRI 在了他的身后。 欧盟和鸟克兰将对美俄付出什么 ? BAU HY 9.3 将会有什么 新的变动 ? 按照历史推演\n,如 今的我们 , 又站 在了怎样的生态位上 ? 01 尼克 松访华后的苏联 美俄要是谈好了 , 我们下一步会怎么 样呢 ?\n子明: 我们回溯 一下 70 年 代 , 基辛 格、尼克松访 华之 后 , 苏联的局势就变得炭炭可 危了。 倒也不用那么悲观 吧 , 那\n时候的大俄和我们没法 比。 +H : 兔子现在跟 美 国的差距 , 难 道比 70 年代苏 联和美国的差距要小 ?\n当时苏联自己的问题就很 大 , 搞什么 出兵阿富汗 , 整得莫斯科奥运会没人去。 子 明 : 这一系列看起来傻逼的外交动 作 , 都\n是苏 联委掉兔子 后 , 产生的一系列后遗症。 子明: 70 年 代兔子和美国和解之 后 , 苏联 的亚洲 地区安全\n成了一个大漏夕。我的理解 是苏联当时急需 打通中亚跟印度之间的联系。 这么看 来 , 我们和当年的苏联很像了。\n好的地方在于兔子和欧洲的关系 要比苏联和欧洲 要好 , 至少形成了钟镁俄欧 的四方格局 , 不会动不动 二 围 一。 TU:\n我们不妨用田岗教练的视角来看 , 苏联之 前是像免 子 的围棋一 样 , 对整个波斯湾地区包围了一 圈 , 令利 亚、埃\n及、埃塞俄比 亚、也 门、印 度、阿富 汗和中亚五 国 。我们和美国交好以后 ,埃及 马上有样学 样 , 阿富汗稀里糊涂\n\n的也没了。 FU: 现在我们可以观望一 下 ,9 . 3 来的人里有 多少是和俄罗斯 关系紧密的。 感觉很 多 , 确实有点不好办了。 子明\n: 所 以 , 我的观点 是虽然美俄谈成 的概率不 大 , 但我们还是要做好相应 的准备。 这还能怎么准备呢 ? 如果真 的谈得 好 ,\n就赶紧增长我们的邀请名单 , 拉拢更多国家 。+v:tisheng2027 , 进提升 知识学习群 , 看 更 多优质 资源\nFU: 差不多是这个意思 , 要赶紧利用这个机会 修复中欧之间的关系 , 赶紧准备欧洲领导人访华。 嗯 ,1980 年奥运 会 , 和我\n们马上开始的活动都是 争取 支持的关键场面。 懂王确定阅兵不来了四 ? TU: 不来了 , 之前有过一个迫边方案。\n哪怕谈崩了也不会来了吗 ? TU: 不会来 了 , 都说了是战略坎诈。 嗯 , 现 在确实也不怎么宣传了。 FU: 2028 年洛杉矶奥运 会 ,\n俄罗斯就会参加了 , 人参考 1984 年 , 兔子参加洛杉矶奥运会。 ARAL RE, KS RVG? 小 泽打到了这 个地 步 , 死 了那么多人 ,\n现在告诉他去接受割地议 ? 且不说鸟克兰人认不认 ? 小泽何以自 处 ? 欧洲如何自 处 ?\n如果俄罗斯撤出乌东 , 那又得是普京输不起了。 俄乌问题两方肯定谈不 拢 , 最多美国解除制裁 , 自己 要点好 处 , 吃完甲\n方吃乙 方 , 俄乌 还得接着向战场放 血 , 搞个 低烈度战争。 子明 : 这是战术层面 的问题。从战略角度 , 则是 如果谈好了 ,\n美国无论如何 都 可以从东欧抽身。 FU: 美俄一旦谈 受 , 对于我们来 说 , 将是影响 颇 大 的外交战略阻碍。而要想转 圆 ,\n只能抓紧最后的 时机 , 争取同样不希望美俄达成协议的利益方的支持 ° 02 跳单 谈 完 了 , 从现场画面来看 ,\n两个人还是很亲密的 这是又动感 情了 ? 看来我们距离合格酒田还有很 KEEN\n两边深详交易的艺术。虽然没谈 成 , 但说马上要 谈成 了 , 利 于双方 再 去 跟别人谈。这样懂王 就可以去 忽悠欧洲重新开价 ,\n人迫使欧洲让 利 , 和否则就跟大毛合 作了。反正是关起门来讲话 , 欧洲也不知道他俩之间 的价 码 , 这得多难受 , 报价高\n就吃亏 , 报价低怕他俩 真 成了。 不过两 油连午餐 都没 吃 , 这 “感情 ”似乎 也没那 么 深 ? 还不 深 , 人家两边都睡上了 ,\n我们却没赚到拉皮 条的 钱 , 用房产 中介的话说 , 跳 单了。 子明 : 跳 单 这个词很灵性。\n那我们现在是不是可以直接约欧盟和小泽吃个夜 宵聊一聊 ? 子 明 : 本月宣布德国总理访华时间。 FU: 皇帝 不急太监急 ,\n现在最急 的是欧洲和乌 ays =o\nFU: 今天会 后 , 下周开始加速减他了。 没谈出停火也减仓 ? 子明 : 本来就谈不出停火。但是明显双方谈得很 好 了。 子 明 :\n普京说服了特朗 普 , 美 国 的国家战略 ,从 施 压俄罗斯 “停火 ”, 转向施压乌克兰和欧洲 “停战 ” ,\n要求其接受俄罗斯的领土主张。 会谈落幕会场 之外的欧洲和乌克兰成为被推出 去 的夸 码。普京和特朗普上演了许久的双 笑 ,\n终于在 本次会晤中将表演推向了高 潮。表面上没有达成实质 性成 果 , 实质上却 都收获了不错 的结局 , 心满意足地 开始\n下一步勒索。 今日的钟镁 俄 , 何尝不是当年的苏美中。 一 END-\n提升知识学习 群 365 一 年 (365 天服务期 ) , 微信源 , 老客户\n进群享折扣。学习群包含以下全部资源 : 一、财经类博主〈财经会员群 258 一年 , 包人以下了个博主内容) 2 ~\nAARON (AK am) 二、时 事类博主〈时事会员群 119 一 年 , 包含以下 11 个博主) , 1、 子明私享汇 (原价 568 元\n/年 ) / 单买 29.9 一年 、米粹米联铺 见闻 RY 599 元 /年 ) / 单 买 29.9 一年 卢克文青云读书会 (原价 699 元 /年 ) / 单买 89.9\n一年 US ee =-! A 1 DURE RAE (OR HT 365 元 /年 ) / IE 29.9 一年 + a de Ok I CUE 328 元 /年 ) / 单 买 19.9 一年 4、 眉树\n西风公众号付费 文章 , 单 买 29.9 一年 是、 江宁知府公众号付费 文章 , 单买 9.9 一 年 三、各种公众 号付费文 , 金政通 鉴\n、局外人的视界、翘 泽异谈、雪球花甲老头、幻纪话你 知 、A 视野、 NEO 换鱼录、冷眼局中人、\n观海谈五行对股市的影响、费盈的小茶馆、蒜在人小时之外、 雷电 海、盛 京剑客、第三章眼观等等公众号付费文章不定时更\n新 , 内容很 多 , 不一一列举 ! 进提升知识学习群包含以上全部内容 , 分享 365 天 , 赠送历史文章 ! 2. 2s MS MIRIRER CLUE\n199 FE/4ED / MELO, 9A /年 ) / 单买 9.9 一生 Py sedi 5. GORI RAB\nO 的内部文章 (原价 400 元 ,年 ) / 单 买 19.9 一年 ”满意 再进群 , 1 6、 户克文知识星球 ;青云 会会员文章 /原价 268 元 /年 )\n单买 19.9 一年更 新 365 天 , | 人、 送历史文章 ! | & 9.", "content_source": "yearly_pdf", "content_chars": 4974, "fq": "A", "il": ""}