{"id": "doc_zst_2025_mystery_noble", "date": "2025-12-06", "title": "全球最神秘的新贵", "summary": "全球最神秘的新贵:全球权贵新生代;神秘资本力量;与庞莱臣/石呆子类似的古董收藏→权力转移信号", "core_claim": "", "snippet": "", "source_url": "", "content": "# 全球最神秘的新贵\n\n时值年末，《时代》杂志（TIME）将2025年度人物授予了八位“人工智能建筑师”。\n\n照片致敬了1932年经典摄影作品《摩天大楼顶上的午餐》——同样是面对百年未有之大变局，同样是面对即将崩塌的旧秩序，只是将打造美国洛克希勒中心的钢铁工人，替换为人工智能基础设施的八位科技巨擘。\n\n时过境迁，搭建21世纪的“摩天大楼”不再需要钢筋水泥，而是机器人、自动驾驶汽车、半导体计算中心、光纤网络和万亿参数的模型。这些“建筑师”正在铺设的，是承载未来全球经济运行的数字地基，他们不仅瞰着物理世界，更以算法视角重塑着人类社会的运行规则。\n\n从左至右，照片上八人分别是扎克伯格，苏姿丰、马斯克、黄仁勋、奥特曼、哈萨比斯、阿莫代伊、李飞飞，算起来，华裔血统占了这八大金刚的三个半。\n\n当然，我们不必对此沾沾自喜，一百年前，准备开创一个新世界的无产阶级工人们，他们辛勤劳动，最终是为幕后洛克希勒家族的大厦添砖加瓦，一百年后，受顶礼膜拜的人工智能巨擎们，作为职业经理人，也是在为隐藏在背后的特朗普家族开创传奇。\n\n而这个传奇，则要从一家名为MGX的合伙基金说起。\n\nMGX由阿联酋副统治者兼国家安全顾问小阿勒纳哈扬负责资金运营，小阿勒纳哈扬也是阿联酋庞大经济帝国的实际掌舵人，他控制着全球最知名的主权财富基金阿布扎比投资局，麾下的MGX则是他为特朗普家族量身定做的一支“家族离岸基金”。\n\n今年以来全球几乎所有超级地缘交易，都能看到MGX的身影，更是有一群全球政商界最顶级的大佬在MGX面前卑微的服务。\n\n譬如，特朗普政府的金主Paypal“黑帮”大佬大卫萨克斯负责产业横向合作，特朗普家族商业合伙人美国中东特使维特科夫负责商务拓展,美国财长贝森特（兼外国投资委员会主席）负责搞定配资，并协调其他部门解决美国行政审批。\n\n该基金通过白宫的政治影响力，深度接入全球政治博弈，打着“利润换和平”的旗号，向各主权国家和富豪家族收取巨额的停战中介费与斡旋费，并以此资金作为本金，从国际资本市场获取巨额的配资，投回到主权国家和富豪家族的产业当中，获取大量股权或者干股，并以股东身份，推动该产业加速融合进入美国人工智能发展的体系当中。\n\n譬如特朗普最为看重的加沙停火后的“日出计划”，就是中东特使维特科夫与女婿库什纳主导交易，沙特筹钱投入MGX，作为保护费，MGX再以此为杠杆，让贝森特组织全球资本与沙特和阿联酋资金投资战后的加沙。全球融的钱负责城市建设，MGX自己的钱则在大卫萨克斯组局的Paypal黑帮的协助下，负责智慧城市搭建。之后女婿库什纳可以赚取源源不断的从加沙重建中赚取无风险的管理费，而掏钱的沙特与阿联酋王室则获得特朗普的安全保证，并提供军购，小萨勒曼的暗杀记者事件一笔勾销。\n\n同样，全球最大的加密货币交易所币安，是中东特使维特科夫的两个儿子（扎克、亚历克斯）与特朗普的三个儿子（小唐纳德、埃里克、巴伦）主导交易，币安老板赵长鹏负责筹钱，将币安此前的稳定币抵押品转换为特朗普家族的稳定币USD1，给予项目的启动资金，MGX再使用这笔启动资金注资币安换取币安的股份，特朗普家族不仅空手套白狼成为币安的股东，特朗普三个儿子持有的稳定币瞬间因此飙升数十亿美元，负责监管币安的贝森特旋即解除了币安的监管并推动赵长鹏获得赦免。\n\n对美国国内的企业，“星际之门”计划也是这么玩的，由中东特使维特科夫与女婿库什纳主导交易，让阿布扎比出几十亿美元给MGX，拉着贝莱德、GIP、微软、英伟达组成的AIP基金，再由贝莱德的向科威特投资局、淡马锡等主权基金募集资金，以400亿美元的价格，完全控制了美国数据中心运营商Aligned Data Centers，这个美国AI算力扩张的关键物理底座，贝森特则力排众议通过审批，将美国的核心资产卖给了“外国人”，掏钱的阿联酋也迅速解除了“小院高墙”的先进半导体进口限制，也不需要将之前G42购入的华为设备全部替换。\n\n正在进行的俄乌停战谈判也是这个模式，由中东特使维特科夫牵头，让俄罗斯寡头们出一笔钱投入到MGX作为启动资金，随后1000亿美元被冻结俄罗斯资产投入一个由美国主导的战后重建基金，将战争赔款转化为一种美俄合作性质的商业风险投资，在此基础上贝森特继续引入西方资本，设立一个单独的美俄联合投资工具，用于投资俄罗斯境内的矿产资源项目，MGX可以从中获得源源不断的分红，俄罗斯则可以在贝森特的支持下，分阶段解除制裁，并通过出让资源和资金以获得乌克兰的领土。\n\n乌克兰与日本韩国也是同理，特朗普的家族基金会潜伏在乌克兰重建基金和日韩投资美国的基金当中，赚取其中的机制性的稳定收益，作为交换，特朗普向乌克兰与日韩等国内的家族提供安全保障。\n\n所以嘛，为啥特朗普一定要标榜自己是和平大使、和平爱好者，一定要说自己停止了多少场战争…….背后都是巨大的家族利益在驱动。\n\n而这所有的停战协议如果站在21世纪“摩天大楼”的视角，东欧负责提供资源矿产，中东负责提供资金，东亚负责运营与算法迭代，美国自己则提供核心算力与核心程序。\n\n面对TIME杂志上的八位天选打工人，特朗普和他家族基金，则会在撮合大国停火的交易过程中，通过MGX不断入股，最终成为全球核心新质生产力的共同股东。", "content_source": "corpus_md", "content_chars": 2148, "fq": "A", "il": ""}