{"id": "doc_zst_0276", "date": "2017-01-26", "title": "涨姿势：国内与国际的政治左右为啥正好相反？（上）", "summary": "涨姿势：国内与国际的政治左右为啥正好相反？（上）", "core_claim": "", "snippet": "涨姿势：国内与国际的政治左右为啥正好相反？（上） 【20170126A01】 近些年以来，很多人觉得自国内的左派和右派与国际上的左派和右派恰恰相反。 问题的根源，在于我们的历史路线，由于斗争需要，普遍非左即右。 但实际上，国际上与国内的主流意识形态，都是三个方向，分别是保守主义、 自由主义和社会主义。 政事堂简单画了一张图： 社会主义者希望向前改革以追求平等， 自由主义者希望向前改革以追求自由， 保守主义希望维持现状或改革倒退。 虽然社会主义者和自由主义者都是要向前改革， 但是改革的方向也略有不同。 以美国为例： 那些依靠技能（互联网+）工作的人，希望社会更加自由，以发挥其才能获得 更大的收益（希拉里的支持者）。 那些依靠自己劳动为生（农村低收入）人群，希望社会更加平等，能够获得更 好的就业", "source_url": "", "content": "涨姿势：国内与国际的政治左右为啥正好相反？（上） \n\n【20170126A01】 \n\n近些年以来，很多人觉得自国内的左派和右派与国际上的左派和右派恰恰相反。 \n\n问题的根源，在于我们的历史路线，由于斗争需要，普遍非左即右。 \n\n但实际上，国际上与国内的主流意识形态，都是三个方向，分别是保守主义、\n自由主义和社会主义。 \n\n政事堂简单画了一张图： \n\n社会主义者希望向前改革以追求平等， \n自由主义者希望向前改革以追求自由， \n保守主义希望维持现状或改革倒退。 \n\n虽然社会主义者和自由主义者都是要向前改革， \n但是改革的方向也略有不同。 \n\n以美国为例： \n\n那些依靠技能（互联网+）工作的人，希望社会更加自由，以发挥其才能获得\n\n更大的收益（希拉里的支持者）。 \n\n那些依靠自己劳动为生（农村低收入）人群，希望社会更加平等，能够获得更\n好的就业、收入以及社会保障（特朗普的支持者）。 \n\n(游戏维多利亚2的设定) \n\n就像核心价值观中，“自由”和“平等”虽然列在一起，但是实际上是很难同\n时实现的。 \n\n因为： \n如果追求自由，由于人类天生资质的差异，在相同的点起跑，在终点就会拉开\n很大的距离，赢者通吃，必将导致不平等。 \n\n而且家族传承，将把这个差距进一步拉大，并形成等级的固化。 \n\n就像我的父辈也许能在北京五金机修厂和瓜爹一起打篮球，而我却不可能混入\n伊顿公学跟瓜仔一起上学。 \n\n相反，如果追求平等，希望共同富裕，则势必需要跑在前面的，让先富带动后\n富。\n\n从小的说，实施阶梯制的个人所得税“劫富济贫”，从大的来说，需要中央分\n税制，从富省拿税收对穷省进行转移支付。因此，分税制与阶梯个所税虽然一\n定程度遏制了贫富差距，但也受支持自由主义的媒体广为诟病。 \n\n再说一下他们三者在改革方面的观点： \n\n自由主义者会积极推动政治改革，只有在民众斗争度高时同意社会改革， \n社会主义者会积极推动社会改革，只有在民众斗争度高时同意政治改革， \n保守主义不愿意做任何改革，只有在民众斗争度高时同意改革。 \n\n因此，我们可以看到在改革开放的前二十年，由于一系列矛盾的激化，在保守\n主义的妥协下，进行了大量的改革： \n在80年代，议会里面自由主义者居多，因此推动了大量的政治改革，如言论开\n放与选举等， \n在90年代，议会里面社会主义者居多，因此推动了大量的 社会改革，如医改、\n教改、社保等。 \n\n如果将三种主义的核心价值推向极致，就会产生意识形态的极化： \n自由主义走向极端，就是无政府主义， \n社会主义走向极端，就是共产主义， \n保守主义走向极端，就是反动主义。 \n\n无政府主义积极推动政治改革前进，推动社会改革倒退 \n共产主义积极推动社会改革前进，推动政治改革倒退 \n反动主义反对任何改革，推动所有已有的改革倒退\n\n共产主义政党在社会改革大踏步的前进，如苏联大锅饭的集体农庄，在政治改\n革上大踏步的后退，如苏联通过秘密警察控制言论、集会和结党。 \n\n而反动主义，就像ISIS那样（极端民族主义），将所有的改革大踏步的倒退。 \n\n社会主义和保守主义目的都是夺取和维护政权，而无政府主义的目标是摧毁政\n权， 因此目前尚未有成功的大型案例， 基本上都是家庭联产承包这种体量。恩，\n也许台湾民进党用爱发电这么一直发展下去也许有机会。 \n\n社会主义者、自由主义者、保守主义者，为了夺取政权，会进行政党化，就像\n我们看国外的那些xx社会党、xx自由党和xx保守党一样，从名字就能看出来他\n们的政治主张。 \n\n而随着党派的发展，党的颜色也会变化，就像国民党，最早是个社会党，后来\n蜕化为自由党，再到最后变成了保守党。 \n11年国民党和袁世凯一起合作推翻满清王朝 \n26年共产党和国民党一起合作推翻北洋军阀 \n49年共产党和民主党派一起合作推翻国民党 \n\n而且，在实际操作过程中，意识形态相近的党派之间还要进行联合（势同水火\n的蒋汪在27年联合剿共），实施两党化，也就是一个台上的执政党，一个台下\n的在野党，进行相互的博弈。\n\n最后说一下为啥国内和国际在左右上面不一致： \n\n由于历史的原因。 \n\n西欧的资本主义国家普遍在选举和言论上更自由，东欧的前社会主义国家普遍\n在医疗和教育上更平等。 \n\n因此，西欧国家的保守主义，和东欧国家的保守主义的含义也是截然不同。 \n\n譬如在西欧，基本上是保守主义政党和社会主义政党的博弈（如英国保守党和\n工党），自由主义政党跟着保守主义政党混。 \n\n原因也很简单，保守主义代表着传统 ，西欧在自由主义的路上狂奔了近百年，\n因此西欧的传统，就是自由。 \n\n既然保守主义代表着传统，那么，东欧在社会主义的道路上狂奔了近百年，自\n然东欧的传统，就是平等。 \n\n同理，在东欧，基本上是保守主义政党和自由主义政党的博弈，社会主义政党\n一般跟保守主义一伙。 \n\n本期实际上是解读一下政事堂发明的红蓝分色。之前写过一 篇，被而和谐了，\n后来百度上还能搜到一个知乎读者写的解读，前段时间也被和谐了。 \n\n因此，政事堂只能通过一个科普文章进行解读了。把文章中的所有的外国人和\n事替换成本国人和事，就OK了。", "content_source": "pdf_split", "content_chars": 2107, "fq": "A", "il": ""}