{"id": "doc_zst_r076", "date": "2026-04-12", "title": "一个蛋糕引发的15亿'血案'", "summary": "一个蛋糕引发的15亿血案:商业纠纷背后的资本与权力博弈;15亿资金的来龙去脉;企业治理与利益输送问题", "core_claim": "商业纠纷背后的政商关系分析", "snippet": "", "source_url": "https://wwyy.org/archives/10971.html", "content": "# 一个蛋糕引发的15亿“血案”\n\n2025年7月，海淀市监局接到一市民举报，怀疑某平台蛋糕有食品安全问题。\n\n8月，市监总局对这块区级举报的蛋糕“提级调查”，总局领导亲自挂帅，亲自推动，从全国抽调200余名执法骨干，分成七个专案组，同时空降七个电商平台公司开始调查。\n\n在20-21市监总局依照《反垄断法》清理互联网资本无序扩张期间，各互联网巨头均深陷漩涡并多次支付顶格的行政处罚，唯有拼多多一家成为了漏网之鱼。\n\n而2025年的这一次调查，其他六家都挺乖的，唯独“砍一刀”的拼多多敢”暴力抵抗”，在专案组调查时，安保负责人当着公安和专案组的面，带着一群人直接冲击办案现场，对执法人员推搡拉扯导致其头部磕地和手骨骨折，被120送往医院。\n\n甚至在专案组与平台员工对话时，一名拼多多工作人员在纸上写下了“沉默”、“不说”等字样，提示接受问询的同事，被发现时，如同电影中的谍报人员一样，将纸揉成一团给“吃”了。\n\n如此暴力对抗专案组，自然讨不了好，市监总局上周五发布公告，七大电商平台“幽灵外卖”，罚款35.97亿元，拼多多以15.22亿元的罚没金额高居榜首，被重重的砍了一刀。\n\n很多人会问：为什么总局会在去年8月发动雷霆行动？\n\n如果关注新闻的话，25年7月30日，中央政治局召开会议，分析研究当前经济形势，部署下半年经济工作，首次提出了：\n\n依法依规治理企业无序竞争\n\n相较于以往会议提及反内卷时说“强化行业自律”，此次直接提出了要“依法依规”治理，就是要对内卷动刀子了，巧合的是，海淀热心群众适时给市监总局送了弹药。\n\n那么，拼多多又为何敢冒天下之大不韪“横刀抵抗”？\n\n当年反垄断查的是“二选一”和“资本无序并购”，反的是资本垄断后的提价，因此拼多多能够躲过一劫，而这一次的查“幽灵外卖”，要的是供给侧改革，清退低端产能，直接打到了依靠疯狂榨取底线以换取流量的拼多多命门，监管拿走算法核心数据时，就像五年前一样，拼多多也遭遇了利益链断裂的生死局。\n\n只是很可惜的，在去年7月政治局会议之后，这个趋势就已经注定挡不住了，国家要推行“清丈田亩”和“摊丁入亩”，将这些挂靠在平台算法庇护下的“数字黑户”摆到桌面上，跟合法经营、承担社会成本的优质实体商户直接竞争，要停止价格战与劣币驱逐良币，给行业龙头地位的企业带来实打实的利润，也为国家带来充裕的社保与税收。\n\n政策调整的背后，是国家主导进行行业利益再分配，将一部分人的蛋糕划归给另一部分人，如今，国家要将空转金融的暴利让利给实体经济，同样，也要将驱逐良币的平台暴利转给实体经济，让真正能干活，干好活的人挣到钱，将物价恢复到合理的位置。\n\n这种政策性的U转，这也是我这两年在群里反复劝我的老朋友，已经买成拼多多股东的“黄赌毒大师傅”赶紧抛了的原因。\n\n同样的，最近拼多多老板黄峥的教父、早期投资人段永平开始琢磨泡泡玛特，当然不是坊间热议的有了年轻的女朋友，而是深刻感受到了这一轮国家政策U转带来的冲击，从生存必需品的极限通缩转向了保暖后的消费溢价。\n\n一个蛋糕引发的15亿“血案”只是开始，砍了拼多多的刀还会继续砍下去。随着国家“依法依规治理企业无序竞争”，接下来还有很多领域将遭遇行政去产能，将低端、隐秘的供给侧产能清退出市场，结束疯狂的价格战，让实体生产的龙头们逐步恢复曾经的利润。", "content_source": "corpus_md", "content_chars": 1369, "fq": "A", "il": ""}