{"id": "doc_zst_0910", "date": "2018-09-27", "title": "中国探月的“灵魂人物”，竟是一个“临时工”？", "summary": "中国探月的“灵魂人物”，竟是一个“临时工”？", "core_claim": "", "snippet": "中国探月的“灵魂人物”，竟是一个“临时工”？ 【20180927A01】 今日，一则情况说明，以其瞠目结舌的内容，引发了网上的疯狂热议。 文中表示，我国未来载人登月以及深空探测的发动机到了最关键的阶段，该所 为此历时十几年时间，投入大量人力物力资源展开的工作，结果，由于一名叫 张小平的“灵魂人物”离职，致使国家重大的战略项目陷入搁置。 这是知乎网友上传的文件： 随着这则文件在知乎上被放出，在众多大V们的带动之下，随即惹来了民意滔 滔。一个决定了中国未来“星辰大海”的科学巨匠，竟然在官僚体制的折磨之 下，落得如此下场。 说起来， 如果政事堂选择跟着骂体制和骂政府， 大概可以很容易收获一篇爆款， 不过，政事堂觉得，探究一下这则报告背后的博弈，以及故事未来的发展，也 许对政事堂的读者群有更大的意义", "source_url": "", "content": "中国探月的“灵魂人物”，竟是一个“临时工”？ \n\n【20180927A01】 \n\n今日，一则情况说明，以其瞠目结舌的内容，引发了网上的疯狂热议。 \n\n文中表示，我国未来载人登月以及深空探测的发动机到了最关键的阶段，该所\n为此历时十几年时间，投入大量人力物力资源展开的工作，结果，由于一名叫\n张小平的“灵魂人物”离职，致使国家重大的战略项目陷入搁置。 \n\n这是知乎网友上传的文件：\n\n随着这则文件在知乎上被放出，在众多大V们的带动之下，随即惹来了民意滔\n滔。一个决定了中国未来“星辰大海”的科学巨匠，竟然在官僚体制的折磨之\n\n下，落得如此下场。 \n\n说起来， 如果政事堂选择跟着骂体制和骂政府， 大概可以很容易收获一篇爆款，\n不过，政事堂觉得，探究一下这则报告背后的博弈，以及故事未来的发展，也\n许对政事堂的读者群有更大的意义。 \n\n通过文件， 我们能够知道， 张小平同志的职称是研究员， 职务是副主任设计师。\n很多人都把职称和职务混为一谈，其实其中却透露出了这个事件爆发的玄机。 \n\n职称的晋升途径，是助理工程师-工程师-高级工程师-研究员，有着非常的严格\n的年限要求，硕士从助理工程师到工程师2年，工程师到高工5年，高工到研究\n员也至少5年。 \n\n而职位的晋升，则是另一条并行路线，是设计师-副主任设计师-主任设计师-型\n号分系统副总师-型号总师。按照张小平的年龄，估计整个航天科工集团，都没\n几个职级这么低的人了。 \n\n举一个不太恰当的例子，就是走过长征的老红军李云龙已经授衔少将了，结果\n却给他安排当了个连长。 \n\n因此，可以确定的是，职称已经到了最高级的张小平，除非是犯过什么重大过\n错，否则肯定是非常的不受上级领导待见的。 \n\n而且，在航空航天领域，咱们国家缺乏缺乏真正意义上所谓的攻坚的专家，因\n为我们的科技，基本上玩的都是对美俄两国的“逆向工程”。 \n\n至于什么是“逆向工程”，就像电影《变形金刚》里面设定的，美国这些年的\n科技发展，就是对从月球捕获的变形金刚，进行逆向工程仿制搞出来的。\n\n所以呢，如果张小平从事的真的是国家登月工程，那么张小平的涉密级别肯定\n是绝密。如果真的要登月，我们也发现了变形金刚呢？ \n\n很显然，一个长期在研究所坐冷板凳得不到晋升的张小平，绝不可能真的从事\n所谓的“国家登月工程”，而且，但凡张小平有一点涉密性质的工作，都会有\n一个脱秘期，绝不可能那么容易就去了民企。 \n\n所以， 西安六所在文件中说谎了， 张小平并不是什么国家登月工程的灵魂人物，\n而是一个很早就靠边站了的边缘人物。\n\n那么，为什么西安六所为什么要在文件中说谎呢？ \n\n这种事儿，如果从政治的角度来看，无外乎是装委屈和推责任两种可能，要么\n是借机说自家现在的薪资已经留不住科研人员了，请求国家给予更多的财政支\n持以提升研究所的福利，要么是无法按时完成上峰制定的 480万吨逆向工程的\n任务，因此就需要一个离职员工当“临时工”来背锅。 \n\n因此，就需要编出来一个故事，通过语言的艺术，把一个在单位早已边缘化的\n人物，塑造成单位不可或缺的灵魂人物流失了。 \n\n当然，排除政治因素，还有一个现实的问题。 \n\n随着马斯克成了SpaceX做民营火箭，国内大量的民企也跟风，在资本的推动\n下进入火箭市场，在各地的咖啡馆里，通过高薪对国营设计院进行大规模的挖\n墙脚，使得国营设计院人才大规模的流失，西安六所成为了重灾区。 \n\n不过国企体制，大家都是笑脸相迎，对于离职也都是好聚好散。但是这么大规\n模的人才流失，院领导完不成国家任务，政治前途也是药丸的。再加上张小平\n离职去的民企，本来就跟研究院在小动力发动机上面有着直接的竞争。 \n\n因此，很可能，西安六所领导也趁机选择了一个平时就不怎么待见的人，来杀\n鸡儆猴，防止人才的继续流失，也同时威慑这些民企的竞争对手。 \n\n而这个文件最大的可能，就是递交给了相关的劳动仲裁机构，要求收回张小平\n分配的国企福利房。 \n\n嗯，这几年西安房价不断飞升，对于一个研究院长期的边缘人物来说，估计是\n半辈子的积蓄。因此，这事儿搁我，也愿意把事儿闹大。 \n\n而更愿意把事儿挑大的，则是张小平目前所在民企的蓝箭航天。一个前几年被\n钢铁侠马斯克的SpaceX做商业化所吸引，类似于贾跃亭搞超级汽车式的创业\n企业。\n\n但是无论是搞超级汽车还是火箭发射，都是长周期重资产的企业，需要资本源\n源不断的进行投入。 \n\n因此，就像马斯克把自己打造成钢铁侠，贾跃亭把自己搞的为梦想窒息，他们\n都需要塑造一个超级英雄，来向资本市场讲故事。而西安六所很配合的出了一\n个文件，也给了蓝箭航天一个现代版的“钱学森”，在媒体的热炒之下，“灵\n魂人物”张小平便可以向资本市场源源不断的要续命钱。 \n\n因此，也就有了文件的流出以及在网上的热点频出。 \n\n但是，这么玩概念有用么？ \n\n马斯克的 SpaceX能够成功，很大程度上在于民主党执政的时候，大规模将\nNASA的军用航天技术无偿向钢铁侠马斯克转移，因此马斯克能够借助美国强\n大的资本力量和全球的商业网络，迅速将一整套的军用技术民用化和量 产化。 \n\n但是， 以蓝箭航天为代表， 目前中国的民用航天领域， 走的却是贾跃亭当年PPT\n造车的路子，通过资本大规模的从相关机构挖人，甩开体系内的支持，另起炉\n灶从头开始。 \n\n要知道，这是与目前军民融合政策背道而驰的，更何况以中国目前的航天技术\n而言，造火箭在没有国家财政补贴的情况下，根本不赚钱。 \n\n而对比一下，贾跃亭乐视那么大的盘子，都被从头做起的超级汽车拖垮了，钢\n铁侠马斯克如今更是危机重重，不得不依靠中国政府提供的强力支持。 \n\n因此，这场被舆论炒起来的火箭风波，最终很可能在泡沫破碎后，以一场闹剧\n收尾。而原西安六所的张小平，在被原单位收回福利房之后，很可能会成为资\n本市场泡沫破裂后的一个牺牲品。 \n\n就像今天新闻中说的： \n任何怀疑、 唱衰国有企业的思想和言论都是错误的。 坚持党对国有企业的领导，\n\n必须一以贯之；国有企业建立现代企业制度，也必须一以贯之。我们要沿着这\n条路笃定踏实地向前推进。", "content_source": "pdf_split", "content_chars": 2504, "fq": "A", "il": ""}