{"id": "doc_zst_2025_japan_counter", "date": "2025-11-17", "title": "反制正当时/数字货币的走势", "summary": "反制正当时/数字货币走势:日本反制时机+数字货币CBDC政策方向", "core_claim": "", "snippet": "", "source_url": "", "content": "反制日本正当时 发 布时间 : 2025 年 11 月 17 晶 民主党执政的美国 , 是战略扩张 , 无 限弹药。 是倾尽武器库存\n来支持乌克兰消耗俄罗斯 , 是不 考虑对自身利益的损害 , 无条件的支持日本印度菲律 EHP Lo EPP “RRR” , “RRR” ,\nRESCH, RMR Ka, SAM, WOR OY RAMA — a, ET A EE, tk ROR HK MM, ANETTA a ° 共和党执政的美国 , 是战略收缩 ,\n有限弹药。 是打完伊朗就退回去和谈 , 是 大幅 削减 对乌克兰 的援助 , 是停掉了 日 本印度菲律宾等前线的反华狗粮 ,\n他要考虑国内的债务问题。 加徽信 : , 进提升 知识学习和群 , 看 更多优质 资源\nTER “BR BAT”, “BGR RGR” , TEAS RAN EER TK, EAL, BCE TE 山 , 痛击伪 军 , 趁着美 俄的虐弱 期 , 秀肌肉 , 秀民主 , 抢\n地盘。 聊完战 略 , 再看战术 对于 日 本这个伪军来 说 , 目前美国进入狗粮大幅 削减的周期 , 此时 , 日 伪 就需要跳出 来 , 展 现\n自 己的 价值 , 以争取拿到仅 剩的狗粮份额 , 争取 主人把他的 狗链子给解开。 因此 , 我们必须要反制日 本 , 但也要控制好火候\n。一方面 , 打 狗 , 是 给其他狗看 的 , 打得越 狠 , 其他 领狗粮的 都会揭量扩量继续向我们吼的代价 与收益。 而日 本 吼 的越凶\n, 越会驱动美国把仅有的狗粮集 中在这个看起 来最患 诚的狗身上 , 可以极大减少美国 对其他国家和地区的支出 ,\n有利于我们接下来 在东亚 战区的统战工作 , 降低统战成本。 加徽信 : , 进提升 知识学习和群 , 看 更多优质 资源\n另一方面 , 打 狗 , 是 给狗主人看 的 , 打得越狠 , 狗主人越 是觉得这条狗基本能搞定我 们 , 就越会忽视 我 们。\n就像当年柏林危机 时 , 趁着老美误以 为叫嚣的老 蒋能搞定 , 我们 速通完成了祖国 大陆的统一。 只要日伪叫得 欢 ,\n美国就越会觉得亚洲战场可以 由 日伪来维持战线 , 这样便可以抽掉更多的有生力量 , 集中于老 美已经疲于应对的东线战场\n(东欧 、中东 、 中南美 ) 。 而 我们的战略战术目标 , 是推动美国调整战略重 心 , 是获取周边 更多的国家支持 ,\n是让美国觉得可以 扶持日伪取代人台伪的工作 , 充当那个马前 卒 , 那么美 国放弃台伪论才会在国会山内获取一 定的支持 ,\n有利 于我们的统一 大业。 因此 , 接下 来 对 日 本就一定要强势反 制 , 打得越 漂亮获得 的国际支持 越 多 , 但千万\n不能有失风度 ,也 不 加徽信 : , 进提升 知识学习和群 , 看 更多优质 资源\n能搞的 过 火 , 我们此刻 只是在抢地 盘 , 还需要普京来 替我们承担美军 的主要攻势。 我们一定要清楚 我们的战略目标 是什么\nKN 正 的 对手是 谁 , 这样才能 把 持好力度。 至 于如何岳他狗日 的 伪 军 , 对标 1943 年的伪军 贾队长就好了。 END\n数字货币的走势 发 布时间 : 2025 年 11 月 17 日 11 月北京线下读者 会 系列内容 随着以赵长观为代表的币 园力\n量跟特朗普完成勾 加徽信 : , 进提升 知识学习和群 , 看 更多优质 资源\n3b, 并将特朗普家族的资产进行了数字货币 化 ,数字 货币将拥有了一种特调 善 退休爹 的属性 , 特朗普在任 期结束前 ,\n必然要出政策支持数字货币 , 使得自身家族能够通过数字货币继续持有大量可 持续 的财富 , 因此 锚定 2028, 数字货币\n\n大概率是有一波涨幅的。 但现阶段 , 随着中 美关系的大幅缓和 , 意味着双方 将一起消灭大量中美之间的灰色地带\n大量持有旧数字货币资产的群体将会 被消灭 , 他们持有的比特币也将会被大量收缴至官方 , 加徽信 : , 进提升\n知识学习和群 , 看 更多优质 资源\n由于官方扫黑采取的是 分肥制 度 , 各级机构都会获得大量 的比特 币 份额 , 其中不 少群体都会选择进行抛售 ,\n因此短期内比特币会领 街数字货币造成一定的跌 tio FE & 1 2028 FA AE th LAIR FEAL, 因此 ,26 年初的数字货币 , 会跟 23 年\n初的黄金类似 , 在货币贬值的大背景下 , 短期内都会 被非理性的 无脑 抛售砸出来一个黄金 dio 延伸阅读 加徽信 :\n, 进提升 知识学习和群 , 看 更多优质 资源\n特朗普宣布特赦赵长鹏 来 源 : AVA 20254104 244 KARR GEARS RAMA, HI 货币交易所币安创办 人赵长月。\n这名加拿大华裔企业家于 2023 年 〈拜 登时期 ) 承 认违反《银行保密 法 》, 因未能建立有效的反洗钱机 制、并违反\n美国经济制裁法 规 , 被判入狱 4 个月 ,并 在 与美国司法部达成的 43 亿美元和解协议 中 , 秤去执行 长职务。 根据《华尔街\n日报》报道 , 特调普家族 自 2024 年 大选以 来经营的加密货币 事业 (2024 年 9 月 , 特朗普家 族成立了 “世界 自由金融公司\n”, 进军加密金融 ) , 收益 已达 45 亿美元 , 并与 由币安低调管理的交易平台\n存在合作关系。这项特赦也因此引发外界对潜在利益 冲突 的质疑。 WAKE RH A, BRA? | 凤凰聚焦 加徽信 : ,\n进提升 知识学习和群 , 看 更多优质 资源\n来 源 : 凤凰网 2025 年 11 月 13 日 《华尔街 日报》也指出 , 币 安为争取赵 长 觅的赦 免 ,已 进行近一年的游说 ,\n使得此次赦免被外界视为 政 治交易 的结果。 据知情人士 透露 , 就在 2024 年美国 大选前 后 , 赵 长胸的私人代表开始与特朗\n普团队接触 , 希 望能够解 决 币安 在 美 国 的合法性 2025 年 5 月 , 赵 长 观律 师团队向特 调善提交了 特 赦申 请。 2025 年\n3 月 , 特朗善家族的 “世界 自由金融公司 ” , 推出了由美国国债背书的稳定 币 USD1。 3 月 12 日 , 币 安宣布 获 得阿布 扎\n比主权基金 20 亿美 元投资。这笔交 易 中最引人注目的 是结算方式是 “ 世 界自由金融公司 ”发 行的稳定币 USD1。\n加徽信 : , 进提升 知识学习和群 , 看 更多优质 资源\n5 月 1 日 , 赵 长 鹏在 社媒 发 布与 USD1 的联合创始人 扎克 . 维 特科夫的合影 ,而 他的父亲正 是担任特朗普中 RES REN LK .\n威 特科夫。 这让一桩金融投资由此被解读出了多重意味 , 中 东资本 的入 场 , 特朗普家族稳定 币的登台 , 赵长觅则\n借此换来一层新的庇护。 短短两周 后 , 特朗 普家族的稳定币 USD1, 宣布正 式登陆 币 安交易 平 台。到目前为止 ,USD1 稳定\n币的总 发行量 中 , 有近九成都 在 币安交易平台上流通。 刚刚 , 全线杀跌 ! 来 源 : 券商 中 国 2025 年 11 月 16 日 11 月 16\n日早间 ,加密 货币市场全线杀跌 。Coinglass 数据显示 , 过 去 24 小 时 , 加密货币市场接近 10 万人被 爆 仓。 有分析指 出 ,\n大跌的主要原因或 许是资金正持续 撤出 加密货币市场。 加徽信 : , 进提升 知识学习和群 , 看 更多优质 资源\n受此影响 , 美 国 总 统特朗普家族从加密货币中获 得 的财富遭遇大幅缩水。自 10 月 5 日比特币触及 126272 美元高点以\n来的一 个 月 内 , 特 朗普及其家族持有的与 加密货 币相关的股票和代币价格均暴跌 约 30%。 END 相关阅读 : [FUME] ARS\n《赵公子们的扫货 经》 (2025 年 11 月 12 日更新 )《 全球灰产的黑色星期五 》 (2025 年 11 月 13 日更新 ) 加徽信 :\n, 进提升 知识学习和群 , 看 更多优质 资源\n提升知识 学习群 365 一 年 (365 天服务 期 ) , 微信资源 , 老客户\n进群享折扣。学习 群包含以下全部资源 : 一、财经类博 主 〈财经会员群 258 一年 , 包含以下 8 个博 主内容新 ) : ORR\n(OE en! 二、时事类博主 (时事 会员群 119 一年 , 包含以下 11 个博主新 ) : 1、 子明私享汇 ( 原价 568 元 /年 ) / 单买\n29.9 一年 、米 糖米联储 见闻 〈原价 599 元 /年 ) / 单 买 29.9 一年 ow 、 大树 乡 谈知识 星球〈原价 199 元 /年 ) / 单 买\n19.9 一年 ) / 单 买 19.9 一年 免费领取资料 、厂三赵阿 0 的内部文章\n(原价 400 元 /年 ) / 单 买 1.9-- 年。免费 试读体验 、户克文知识星球 + 青云会会员文章 ! 原价 268 元 /年 ) 单买 19.9 一年\nsour 、卢克文青云读书会 ! 原价 699 元 /年 ) / 单 买 59.9 一年 ae Rt BUY MALS (WR 365 元 /年 ) / ME 29.9 一年 、 欧洲\n金能会 员 群文章 (原价 328 元 /年 ) / 单 买 19.9 一年 16、 眉村西风公众号付费文章 , 单 买 29.9 一年 11、 江宁知\n府公众号付费 文章 , 单 买 29.9 一年 a a es 四、各种公众 号付费文 : 多政通鉴 、局外人的视界、匮 泽异谈、雪球花甲老头\n、幻纪话你知 、A 视野、 NBO 摸鱼录、冷 眼 局中人 、 观海 谈五行对股市的影响、费最的小茶馆、赢在八小时之外、 雷思\n海、盛 京剑客、第三章 眼 观等 等公众号付费文章不定时更 新 , 内容 很 多 , 不 一 一列举 !\n进提升知识学习群包含以上全部内容 , 分享 365 天 , 赠送历史文章 !", "content_source": "yearly_pdf", "content_chars": 4194, "fq": "A", "il": ""}