{"id": "doc_zst_2025_maga_index", "date": "2025-03-09", "title": "美国经济危机最重要的指标", "summary": "美国经济危机最重要的指标:判断美国经济是否陷入危机的关键指标;就业/消费/信贷/市场信心;指标恶化=危机临近;特朗普政策对指标的影响", "core_claim": "'赢麻了'=反向经济指标(越造神越危险)；历史规律(苏联/阿根廷/朝鲜)", "snippet": "", "source_url": "https://wwyy.org/archives/9860.html", "content": "--- title: \"美国经济危机最重要的指标\" source_url: \"https://wwyy.org/archives/9868.html\" source_type: \"xitalk mirror\"\nclaimed_account: \"子明解读 / 顾子明\" date_guess: \"2025-03-09\" description: \"最近一段时间，美国白宫官网几乎天天都\n是“赢麻了”的宣传，国会山的共和党议员们仿佛劳动党党员的鼓掌，特朗普也变得天天宣传自己战无不胜，说自己超过了华\n盛顿。搞的朋友们纷纷调侃，原来美帝也有今天。调侃归调侃，这些夸张而诡异的“赢麻了”出现在美帝，是一个非常明确的\n信号，美国很快要进入“苦难行军”的状态...\" ---\n# 美国经济危机最重要的指标\n最近一段时间，美国白宫官网几乎天天都是“赢麻了”的宣传，国会山的共和党议员们仿佛劳动党党员的鼓掌，特朗普也变得\n天天宣传自己战无不胜，说自己超过了华盛顿。\n搞的朋友们纷纷调侃，原来美帝也有今天。\n\n调侃归调侃，这些夸张而诡异的“赢麻了”出现在美帝，是一个非常明确的信号，美国很快要进入“苦难行军”的状态。\n甚至这种苦难行军若是处理不当，全球经济也可能会被美帝带到沟里，造成巨大的经济危机。\n分析逻辑之前，先说一个我小时候看过的故事，《东周列国志》里面，大改革家管仲教打工人唱歌。\n说的是公子小白装死先回国当上了齐王，听从鲍叔牙的建议，准备重用死对头管仲为相来开启改革。于是骗鲁国国君抓管仲送\n给他，好亲自杀了泄愤，鲁国国君就把管仲关入囚车押送回齐国，管仲猜到了这是鲍叔牙的计谋，又担心这个计谋被鲁国大夫\n们看破，于是创造了一首《黄鹄》之歌，教那些打工人传唱。\n这歌听名字就跟陈胜的“鸿鹄”很类似，贼特么的励志，搞的这帮打工人一边唱歌一边走路，忘记了疲倦，也忘记了饥饿，一\n天走了两天的路程，果真赶在追兵之前逃离鲁境，投入了齐桓公的怀抱，然后齐国的改革就这么成功了。\n故事虽然有点扯，但话糙理不糙，想要让打工人饿着肚子奔跑，就需要有人来唱高调，让大家忘记疲惫和饥饿，把改革的阻力\n降至最低。\n譬如以米莱“电锯”改革而闻名的阿根廷。\n70年代末由军政府执政期间，就推行过一轮特朗普/米莱式的改革，策略跟现在一样，都是通过经济自由化、私有化、放松管\n制，限制福利，贬值汇率等措施，来刺激经济发展与压低通胀。\n这种改革长远来看，的确会推动产业升级，但短期也会带来大规模的失业，对于当代打工人来说是非常痛苦的，阿根廷的精英\n阶层于是便选择了让马岛“赢麻了”的方式，来麻痹阿根廷的打工人。\n那几年，阿根廷的国家媒体就像现在美国白宫官网一样，天天宣传自己从一个胜利走向另一个历史性的胜利，各种Make Arge\nntinas Great Again的口号，把总统加尔铁里塑造成了一个战无不胜无所不能的铁人，跟阿根廷国父圣马丁并列，不断击败敌\n人，收复阿根廷自古以来的领土。\n当然，胜利的牛皮最后被戳破了，不仅改革戛然而止，阿根廷的经济也陷入到一轮大衰退。\n如今，米莱的好朋友特朗普，也在试图进行跟半个世纪前阿根廷一样的改革之路，所以他也需要重演半个世纪前的改革之路，\n从巴拿马到格陵兰，从加拿大到墨西哥，从俄乌冲突到哈以冲突，他都需要像一个小孩子那样，不停的获得胜利。\n如果我们抛开意识形态的墨镜，过去半个多世纪以来，无论东西方，无论左右翼，无论成败，无论纳粹还是苏维埃，很多大刀\n阔斧的经济改革，为了让打工人饿着肚子快跑，为了抢在竞争对手的前面，来完成这些痛彻骨髓的改革，都会伴随着造神与宣\n称”赢麻了“”的行为。\n以我们最为熟悉的，30年代苏联搞全面工业化、集体农场，50年代朝鲜搞集体化、消灭私有经济，莫不如此，甚至我们还能从\n特朗普2.0身上和他的媒体狂轰滥炸中，找到他德国祖先小胡子的影子。\n调侃归调侃，在美国搞造神运动，就算共和党的议员们年轻不懂事儿，共和党背后那些已经持续了数百年的家族与企业，会不\n懂么？\n经历了一二战，经历了无数次经济危机，见证了社会主义阵营一个个国家搞工业化，扶持了一个个的自嗨赢麻式的军政府，操\n刀了南美洲与苏联休克的他们，对这些玩意太门清了。\n但他们更清楚，这一轮AI带来的生产力变革与劳动力大淘汰中，不仅需要向海外掠夺财富，向未来透支金钱，更需要的是，大\n剂量麻药和新增就业来止痛，防止失业民众变成李自成和张献忠，把资本家们拖出去挂路灯。\n此时，美国的改革精英阶层们，不仅需要特朗普把就业带回美国，降低通胀，更需要通过对特朗普的造神运动中，搞精神胜利\n麻痹民众，才能在才能在不断“赢”之中，实现无痛的“麻了”。\n因此，回顾历史就会明白，“特朗普赢麻了”，也将是未来两年最重要的宏观经济指标，影响着美国股市、汇市以及债市。\n一旦台上的特朗普停止或者弱化对自己搞神化，就意味着美国这一轮的改革成功或者走势良好。\n而越是当美国政府极力加码配合宣称特朗普赢麻了，美国经济就越是迈向特朗普改革带来的暴风漩涡。\n正文完\n发表至： 顾子明\n2025-03-10", "content_source": "yearly_pdf", "content_chars": 2085, "fq": "A", "il": ""}