{"id": "doc_zst_2024_body_fake", "date": "2024-09-01", "title": "身体假新闻频出的计谋", "summary": "【核心论点】身体假新闻频出的计谋=政治人物健康谣言是有组织的信息战。分析假新闻的政治目的:试探/施压/制造不稳定。", "core_claim": "", "snippet": "", "source_url": "", "content": "《身体假新闻频出的计谋 ，看更多优质付费资源 \n没自上海线下读者会 发布于2024 年9 月2 日 暑假结束了， 老板都重回新闻联播了， 可是针对老板健康的假新闻依旧不断,\n这种一眼假的小道消息, 能够被广泛传播， 是因为制造小道消息的群体， 本身就来自于体制内部， 所以他们制造的假新闻，\n都是有鼻子有眼， 看起来非常的真实。 相较于蓝党的领袖只是名义上的， 离了谁都照样运转， 红党和新党从政治结构上，\n都非常依赖于领袖， 领袖就像星际类面的主宰， 一旦消失， 微信：\n，看更多优质付费资源 整个团体就会陷入崩溃。 20 多年前，386 作为核心的时候\n当年反对力量就是这么玩的， 一遍一遍的对他的健康造谣, 后来也如他们所料， 在386 死后，群龙无首的J 派，\n以肉眼可见的速度在消亡并退出历史舞台。 因此，制造领袖身体状况问题， 是对付红党和新党的最佳手段之一，\n只要大家都认为领袖身体出了问题 各路野心家就会不受控制的涌出， 基层就会想着把老板交办的事情拖一拖，\n甚至还会有二楞子海瑞上治安疏， 即使老板身体没问题，也能给老板气病了 \n微信：\n，看更多优质付费资源 《背景神秘的侯亮平(人民名义系列3) \n源自8 月28 日群聊发布于2024 年9 月2 日 侯亮平(钟小艾)的背景很强，这个强针对的是普通人，\n远没有强到网上所谓的国级。 就像省级领导人的孩子赵瑞龙， 争夺的是市级产业和资源的分配权。\n国级领导人的孩子们，争夺的是省部级产业和资 源的分配权， 有多大的屁股，穿多大的裤衩，\n李的儿子在山西主导煤电网络的利益再分配， 陈的儿子在国开行主导国家开发资金的再分配，\n邓的儿子在残联主导全国福利资金的再分配。 国级领导孩子的手套， 或是成为大型央企的负责人\n或是成为行业或者地域的大哥， 哪怕海峰公司出身的赵伟国，麾下的清华紫光， 也一度成为了3000 亿的半导体巨头，\n侯亮平只不过是一个撬动汉东的棋子， 远没有介入到汉东的利益分配大局， 他帮助沙瑞金打赢了赵立春, 微信：\n，看更多优质付费资源 \n也不过是把(副局级)的括号去掉而已 若真是国级领导人的儿子或者女婿: 身边早就会围绕着一群白手套，\n等着帮接收赵家垮台后的汉东产业， 而身边白手套都没有的候亮平， 总不能临时抱福脚，启用蔡成功。\n各方都在吹嘘和逢迎侯亮平， 只不过是把他当作一个孙悟空， 要让他去汉东大闹天宫， 侯亮平的神秘背景,\n\n就是孙悟空级别的神秘背景， 真正的国级二代， 是如来家的老二唐三藏， 所有人都对他的身份心知肚明，\n有着几十个护他安全的团队， 一路走来必然都是有惊无险， 参考沈腾电影抓娃娃， 一个富商的儿子都有数十人的团队随行,\n副国级的孩子， 如果不是当废柴来养， 2 微信：\n，看更多优质付费资源 怎么也不会比沈腾寒酸的多。 而且，所有的国级领导人，\n必然都是政治山头的一部分， 赵立春不仅在汉东有一批铁杆小弟， 他必然也是某个中央大佬的铁杆小弟。 政治斗争当中，\n一旦两派明确了敌对关系 双方将会开启拼命的对子行为， 就像这一年多来的贵州和江西， 杀得那叫一个人仰马翻。\n人民名义只拍了对汉东赵家的清算， 但是赵立春的老板如何反击，\n并不会在这部电视剧里面展现按照“枪打出头鸟”的逻辑， 刺头侯亮平背后若是有政治力量，\n必然是赵立春老板的首个攻击目标。 所以，侯亮平不可能是国级背景， 他不过是一条有资格咬人的狗，\n国级领导人也绝不可能让自家的孩子， 去给一个省级干部当马前卒， 不仅在汉东吃不到什么好处，\n还会导致整个派系被裹挟入政治漩涡充当其他派系的马前卒， 引发一系列难以想象的政治灾难\n\n，看更多优质付费资源 \n内客延展自杭州线下读者会 宗教部分发布于2024 年9 月2 《不被待见的特斯拉》 日 马斯克的特斯拉是2 号L 的政绩工程，\n但是从中央不断摇摆的态度来看， 显然特斯拉不是中央的2 号工程， 若是一国PM 力推的项目， 此刻早应该在国内飞起。\n还是那句话， 从老板肚子里蛔虫的C 的身上, 能够显然看出来老板的态度， 那就是老板并不怎么喜欢马斯克。\n不是老板不喜欢科技， 恰恰相反， 老板坚信科技是第一生产力， 但是老板喜欢的科学家, 是用科技荣耀主的牛顿,\n微信：\n，看更多优质付费资源 \n不是赚到了点钱， 就试图用钱来介入政治的马斯克 边在美国扶持特朗普的二号， 一边在中国扶持老板的二号，\n马斯克的思路是非常清晰的， 跟梅屋庄吉在长崎资助孙中山， 虞洽卿在上海投资蒋介石类似都是在百年未有之大变局下，\n资本家通过资助一个年轻的实力派， 成为新政权最主要的股东， 用权力为新的产业结发展保驾护航\n但老板不是蒋介石和孙文， 老板喜欢给高职务、高薪水、高奖金, 但是老板不喜欢被入股， 被别人拿走自己收税的权力。\n老板允许资本家作为一个职业经理人， 凭借业绩赚的盆满钵满, 这样他作为绝对控股的大股东， 可以分到海量的税收，\n他喜欢的是沙特资本和德国企业 只想赚钱，没有政治诉求的资本 所以老板肚子里蛔虫的C， 微信：\n，看更多优质付费资源 就会集合全北京之力， 帮助小米的雷军完成SU7,\n因为雷军这种没有政治诉求的资本家， 小米这种只赚辛苦钱的企业， 就是老板心目中应该支持的对象，\n可以不惜代价的支持他们做大。 老板认为， 好的企业应该是做有型的产品， 而不是搞平台收保护费的，\n所有试图建立收税平台的垄断型企业， 都会引发他的应激反应， 苹果、特斯拉、蚂蚁，莫不如此，\n对此，最懂他的C，都会心领神会", "content_source": "yearly_pdf", "content_chars": 2273, "fq": "A", "il": ""}