{"id": "doc_zst_0675", "date": "2018-02-04", "title": "从俄罗斯寡头清单，看国际油价变化", "summary": "从俄罗斯寡头清单，看国际油价变化", "core_claim": "", "snippet": "从俄罗斯寡头清单，看国际油价变化 【20180204A01】 近日，美国财政部公布了一份“寡头政客清单”，其中包含了数百名俄罗斯政 要和商界精英，由于名单中所有的人均为俄罗斯的实权人物，因此也被坊间成 为“克林姆林宫清单”。 该名单的诞生，源自奥巴马政府时期，对乌克兰危机中，俄罗斯强吞克林米亚 而进行的调查制裁措施。 因此，这份该名单一公布，便引发外界对于美方对俄新一轮制裁的担忧。俄联 邦国际事务委员会主席甚至表示，这“标志着美国要和俄罗斯打破双边关系”。 普京更是表示，这就是美国把所有俄罗斯人都视为敌人的一大证据。 而再加上昨天俄罗斯空军一架SU25战机， 被“某西方大国”扶持的叙利亚恐怖 组织使用境外提供的便携式防空导弹将战机击落。很多人都认为美俄关系即将 迅速恶化。 不过， 政事堂却不", "source_url": "", "content": "从俄罗斯寡头清单，看国际油价变化 \n\n【20180204A01】 \n\n近日，美国财政部公布了一份“寡头政客清单”，其中包含了数百名俄罗斯政\n要和商界精英，由于名单中所有的人均为俄罗斯的实权人物，因此也被坊间成\n为“克林姆林宫清单”。 \n\n该名单的诞生，源自奥巴马政府时期，对乌克兰危机中，俄罗斯强吞克林米亚\n而进行的调查制裁措施。 \n\n因此，这份该名单一公布，便引发外界对于美方对俄新一轮制裁的担忧。俄联\n邦国际事务委员会主席甚至表示，这“标志着美国要和俄罗斯打破双边关系”。\n普京更是表示，这就是美国把所有俄罗斯人都视为敌人的一大证据。 \n\n而再加上昨天俄罗斯空军一架SU25战机， 被“某西方大国”扶持的叙利亚恐怖\n\n组织使用境外提供的便携式防空导弹将战机击落。很多人都认为美俄关系即将\n迅速恶化。 \n\n不过， 政事堂却不这么看， 而且在看了美政府的“俄寡头政客清单”名单之后，\n反而感到了一丝寒意。 \n\n这份大名单中96个所谓的“俄罗斯寡头商人”，其实就是福布斯俄罗斯100富\n豪榜中的前96位。而后排行榜后四位没有入选的原因，很可能就是他们排行榜\n上的身价低于10亿美金。 \n\n如此不负责任的名单，也就是说，这个排行榜是直接照着福布斯排行榜抄出来\n的。而且，其中前96名的“寡头商人”中，不少还是以反对普京而著称，更不\n要说有几个公认的普京“白手套”，也没有出现在这份清单之上。 \n\n这事儿是十分诡异的，要知道，奥巴马政府时代就开始筹备这份名单，美国政\n府不可能会出现这么大的纰漏。 \n\n因此，这也意味着，特朗普政府并非像表面上那样，和普京政府斗得针尖对麦\n芒，实际上，特朗普这次根本就不准备制裁俄罗斯，甚至两个“普”字辈的独\n裁者，还一起对外演了一出“双簧”。 \n\n所以政事堂判断，特朗普顶着国会压力“放弃制裁”俄罗斯，很可能是因为需\n要普京的配合，在2018迅速大幅提升国际油价，而进行的政治交换。 \n\n之前政事堂文章解读过，依靠石油钢铁集团上台的特朗普就任总统之后，很意\n外的开始收拾伊朗、委内瑞拉，并在伊拉克境内鼓动库尔德独立，支持沙特家\n族政变，默许沙特围剿卡塔尔。其中根本的原因，就是这五个国家是全球石油\n储量排名前五的国家，只有控制他们的产能，才能控制全球油价。 \n\n虽然美国可以通过制裁和傀儡政府的方式，控制这五大产油国，但是，同为联\n合国五常的俄罗斯，却不是特朗普能控制的。而且，俄罗斯也是唯一有工业能\n力，能够迅速提升石油产能的国家。\n\n因此，如果特朗普的油价上涨计划无法与普京达成一致，那么油价一涨，俄罗\n斯顺势增加产能，特朗普可就是为了俄罗斯的伟大复兴在做贡献了。 \n\n所以，特朗普上台之初，就对特普京表示了极大的好感，甚至特朗普上台才一\n年，本来摇摇欲坠的亲俄叙利亚政府，竟然反败为胜，击溃了美国背后支持的\n反对派。 \n\n很显然，这背后有着一场特朗普和普京之间的政治交易。虽然此事儿很多人心\n知肚明，但是智商捉急的美国民主党，就是抓不住“政治献金交易”的石锤证\n据。 \n\n因此，这次“虚假制裁”名单的公布，也意味着，特朗普政府大概率是铁了心\n要在2018年将国际油价迅速拉升。 而手握对俄罗斯制裁的达摩克利斯之剑的特\n朗普，也能保证普京的配合。 \n\n说了国际，再顺着油价，把镜头转回国内。 \n\n中国CPI两个重要参数，一个是猪肉，一个是石油。如果2018年的国际油价，\n按照特朗普的意愿大幅拉升，势必导致中国通胀压力大幅提升，物价 CPI将大\n幅上扬。 \n\n而原本在美国加息、缩表、减税三连击压力之下，再加上国内 CPI上涨，势必\n给予我国政府极大的加息压力。 \n\n而我国政府今年开始，对房地产供给侧改革，试图通过降低开发贷规模，让房\n地产泡沫软着陆。而倘若一旦被迫加息，巨额的利息增 长势必导致连锁反应，\n加大房地产软着陆变为硬着陆的可能。 \n\n虽然很多人都在鼓吹房价暴跌，但是我们要明白，房价硬着陆第一个不答应的\n就是咱政府。 \n\n所以，对于极度依赖石油进口的我国政府来说，想要降低 CPI，一方面通过期\n货的手段，保障远期的石油供应，另一方面，则是加大农业现代化，向城市提\n\n供更廉价的农副产品，以及开拓国内市场规模。 \n\n而这两方面，前者，是特朗普访华时带走的2500亿大单，后者，则是今天出台\n的比以往严厉的多的中央“一号文件”，对农村进行“供给侧改革”，并给出\n了路线图。 \n\n最后，就这特朗普这事儿，再说几句跟大家切身相关的油价和股市。 \n\n政事堂过去一年多以来，文章中一直看涨国际油价、石油股和 A股的大盘股，\n认为美国会从朝鲜抽身的逻辑，其实很简单。 \n\n共和党的金主是石油钢铁集团，而如今美国总统和国会都是共和党控制，若真\n想推动一件事情，即使有阻力，通过利益交换和政策倾斜，也能够最终实现。\n握着全球最强大军队的美国政府，想涨个油价还能做不到么？ \n\n而一年多来，中国的大A股的二八分化，也是这个道理，嗯，你懂的。 \n\n甚至这一年多来，就像阿里、腾讯以及连续蛇吞象的融创，为了大规模扩张，\n也需要提振市值，来增大融资能力。 \n\n因此，完全不会技术分析而只懂点政治的政事堂，对于资本市场特别喜欢这张\n图：\n\n谨以此图向Wx同志表示敬意", "content_source": "pdf_split", "content_chars": 2144, "fq": "A", "il": ""}