{"id": "doc_zst_0921", "date": "2018-10-08", "title": "让大佬“窒息”的贾跃亭，背后隐藏的故事", "summary": "让大佬“窒息”的贾跃亭，背后隐藏的故事", "core_claim": "", "snippet": "让大佬“窒息”的贾跃亭，背后隐藏的故事 【20181008A01】 昨日， 恒大的一纸公告， 让令大佬“窒息”的贾跃亭， 再一次成了“负心汉”。 公告显示，贾跃亭在香港提出仲裁，要求剥夺恒大在法拉第公司相关协议下的 权利。 嗯， 从蜜月期的载笑载言到公开撕破脸， 贾跃亭与许家印仅用了3个月。 随着恒大公告的放出，中国互联网上几乎一边倒的剑指“下周回国”的贾跃亭， 例如“农夫与蛇”，“负心汉”，“白武士杀手”，“上过8次失信名单”， 以及拿人钱财却想踢人出局的说法，遍布于网上。 甚至大家翻起了旧账，从张艺谋、孙俪、黄晓明、孙红雷等一大批影视大碗被 贾跃亭坑的历史说起，到王健林、马云、柳传志、孙宏斌、许家印等一大批的 国民老公公和国民爸爸，贾跃亭也成了一个“坑爹”小能手。 不过，作为活活一路把乐", "source_url": "", "content": "让大佬“窒息”的贾跃亭，背后隐藏的故事 \n\n【20181008A01】 \n\n昨日， 恒大的一纸公告， 让令大佬“窒息”的贾跃亭， 再一次成了“负心汉”。 \n\n公告显示，贾跃亭在香港提出仲裁，要求剥夺恒大在法拉第公司相关协议下的\n权利。 嗯， 从蜜月期的载笑载言到公开撕破脸， 贾跃亭与许家印仅用了3个月。 \n\n随着恒大公告的放出，中国互联网上几乎一边倒的剑指“下周回国”的贾跃亭，\n例如“农夫与蛇”，“负心汉”，“白武士杀手”，“上过8次失信名单”，\n以及拿人钱财却想踢人出局的说法，遍布于网上。 \n\n甚至大家翻起了旧账，从张艺谋、孙俪、黄晓明、孙红雷等一大批影视大碗被\n贾跃亭坑的历史说起，到王健林、马云、柳传志、孙宏斌、许家印等一大批的\n国民老公公和国民爸爸，贾跃亭也成了一个“坑爹”小能手。 \n\n不过，作为活活一路把乐视写死的政事堂，对翻旧账和落井下石没啥兴趣，更\n关心的是大佬之间的政治博弈， 以及事件的未来走向。 （新闻原稿我就不放了，\n网上多得是） \n\n首先，重申一个之前详细论证过的问题，不要以为乐视网和乐视法拉第两块资\n产不值钱。 \n\n今年年初新乐视智家中，融创、腾讯、京东、苏宁、恒大、 TCL等巨头们就入\n股了，各方达成了一个均势平衡。更不要说，上个月孙宏斌又通过司法拍卖的\n方式接盘了乐视网的股票。 \n\n而法拉第汽车就更不用说了，贾跃亭掏空了创业板一哥的乐视网，去搞法拉第\n汽车，无论时间成本还是大规模投入的资金，都意味着哪怕贾跃亭是个猪，这\n么砸钱砸时间也能给法拉第砸出来价值。\n\n所以，就像最近那么多P2P的旁氏骗局破裂，可最后大家还是能拿回不少本金\n一样，有着山西某家族扶持，一度冲击BAT巨头的乐视，再烂其资产也不可能\n一钱不值。 \n\n所以，数字就不列了，就像大量的巨头们“混改”万达一样，被誉为庞氏骗局\n的乐视，也吸引了市场上大量的巨头前来。 \n\n骂贾跃亭是庞氏骗局的老百姓，一样可能被互联网金融骗，但是分食乐视的孙\n宏斌、许家印、马化腾、刘强东、张近东、柳传志们。哪一个不是中国资本市\n场上，食物链最顶端的猎食者呢？ \n\n就像昨天文章中，我引用的“铁锅炖自己”的那张图说的那样，未来在政府强\n力管控房地产的大背景之下，资金会很难的。 \n\n这几年来，几大民营房地产巨头都在积极转型。而贾跃亭的国内和美国的两块\n资产，分别为融创和恒大两个房地产巨头，提供了跨界转型的契机。 \n\n所以，就像孙宏斌入主乐视，一样开启人士布局，控制乐视网，与贾跃亭的乐\n\n视控股分庭抗争一样。从许 家印入股法拉第之后，很快就控制了法拉第中国，\n与贾跃亭的法拉第美国分庭抗争。 \n\n所以，相比于入股马化腾和刘强东的白武士高瓴张磊，入股之后不仅不干涉还\n提供大量的增值服务并帮着吹牛逼，贾跃亭的“白武士”老孙和老许，嘴上一\n边说老贾不咋地，但是在处置乐视资产上，身体却是很诚实的。 \n\n然后，在从贾跃亭的角度来看一下。 \n\n最近一年多的时间里，孙宏斌一路鲸吞乐视资产，甚至公开的侮辱，贾跃亭都\n一直忍着，即使股票被法院拍卖，也没有公开撕破脸皮。 \n\n而从恒大的公告中能够看出来，贾跃亭此次寻求仲裁，而不是与许家印进行谈\n判，这意味着，贾跃亭肯定已经被逼到了死胡同，才会走到撕破脸的仲裁这一\n步。 \n\n而能够把贾跃亭逼死的唯一可能性，绝对不是钱，而只可能是法拉第汽车的控\n制权。 \n\n过去几年的时间里，贾跃亭掏空了拥有庞大现金流的乐视的资产去搞新能源汽\n车，更是在去年放弃国内的一切，逃至美国造车。 \n\n因此，对于贾跃亭来说，法拉第不仅是他孤注一掷的心血，更是他唯一翻盘和\n洗刷身上污名的机会。 \n\n所以，意图转型的许家印，与孤注一掷的贾跃亭，在法拉第未来的控制权上面\n的冲突，终于爆发了。 \n\n今年6月，恒大和贾跃亭签订协议，如果法拉第在2019年不能实现量产，贾跃\n亭将失去AB股中，1股10票的权力，恒大将主导法拉第的经营。 \n\n根据恒大的公告，今年7月，贾跃亭的首笔8个亿美金的恒大付款已经用完了，\n贾跃亭要求恒大提前支付7亿美金。双方签订了补充协议，同意在满足支付条\n\n件下，提前支付这7亿。 \n\n根据之前财新的报道，贾跃亭对于供应商的欠款，大概也就 1个亿的美金，在\n极短的时间内，烧掉6个亿美金，这绝不是在法拉第美国毫无大动作的贾跃亭\n所能做到的。 \n\n（注：以下内容为推测） \n\n因此，政事堂判断，就像孙宏斌驰援贾跃亭的百亿资金，基本都用于了偿还关\n联银行的乐视网贷款，而非解决乐视系的供应链现金流一样，恒大给贾跃亭的\n这笔七个亿的美金中的绝大部分，大概率是花在了恒大所控制的法拉第中国。 \n\n所以，目前法拉第形成了两条线，法拉第美国的FF91和法拉第中国的FF81，原\n本的一条产品线变成了两条， 成本激增的同时， 广州的土地购置和厂房的建设，\n消耗掉了原本贾跃亭用于法拉第美国量产所需的资金。 \n\n所以，也才有了贾跃亭和许家印很快进行的补充协议，承诺将原本明年年底才\n支付的款项（扩大产能所需要的资金），改为今年年底前支付（成为了量产需\n要的资金）。 \n\n但是，由于贾跃亭的信用破产，法拉第的供应链都需要现款现结，恒大方的迟\n迟未支付法拉第量产所需要的资金，使得贾跃亭在面对之前对赌协议中，明年\n一季度量产将成为泡影。 \n\n所以，被逼到绝路上的贾跃亭，选择撕破脸，把法拉第未来的未来，交到仲裁\n来解决。 \n\n老读者们都应该知道，我可能是自媒体中，最早开始说贾跃亭要垮的，而且系\n列文章，每一步都精准的预判，所以，真的没有替贾跃亭洗白动机。 \n\n只不过， 乐视的垮台背后， 我描绘的是一次历史的进程。 相比于其他的企业家，\n被大佬们分食的乐视，没有死在寒冬而是深秋。\n\n所以，看着高呼着未来要过冬的列位大佬们，我真心的希望大家不要光去嘲笑\n贾跃亭这个为了梦想而窒息的奋斗者，而是应该去反思，曾经辉煌到极致的乐\n视，是如何轰然倒塌，廉价的沦为别人餐桌上的盛宴。 \n\n就像杜牧说的，后人哀之而不鉴之，亦使后人而复哀后人也。", "content_source": "pdf_split", "content_chars": 2469, "fq": "A", "il": ""}