{"id": "doc_zst_2024_uturn_side", "date": "2024-08-18", "title": "U转的选边站队", "summary": "【核心论点】U转的选边站队=全球格局U转中各国必须选边;中立不再是选项。", "core_claim": "", "snippet": "", "source_url": "", "content": "--- title: \"U转的选边站队\" source_url: \"https://wwyy.org/archives/8854.html\" source_type: \"xitalk mirror\"\nclaimed_account: \"子明解读 / 顾子明\" date_guess: \"2024-08-18\" description: \"伴随两个月前，拜登电视辩论惨败给特朗\n普，很多政治力量开启了搅动。多家五眼联盟的英澳航空公司集中宣布暂停飞往中国的航班，一些国际邮轮公司也取消了中国\n航线。虽然有经济因素，但这些去年费劲心机，走了无数关系，做了大量政治交易搞出来的航线，才运行一年，就骤然中断。\n有趣的是，近期，中国境内的朝鲜劳工近期...\" ---\n# U转的选边站队\n伴随两个月前，拜登电视辩论惨败给特朗普，很多政治力量开启了搅动。\n多家五眼联盟的英澳航空公司集中宣布暂停飞往中国的航班，一些国际邮轮公司也取消了中国航线。\n虽然有经济因素，但这些去年费劲心机，走了无数关系，做了大量政治交易搞出来的航线，才运行一年，就骤然中断。\n有趣的是，近期，中国境内的朝鲜劳工近期也在陆陆续续遣返回国。\n这也是五年前金将军费劲心机，在大连棒棰岛陪了不少笑脸才搞定的。\n区别大概是，相较于欧中航班的利润相对有限，朝鲜在华劳工收入，是朝鲜政权的生命线。\n但朝鲜劳工大约是有底气返国的，\n本月的外交部例行记者会，有记者提问上个月朝鲜停战71周年纪念活动，俄越古等驻朝大使均出席，唯独没有中国。\n同时，大连棒棰岛的铜脚印，也在今年上半年被悄悄的抹除了。\n其中的原因之一，大约是今年以来，俄朝关系急剧升温，普京访问朝鲜，大量的俄式采购出现在了朝鲜，卢布取代了人民币。\n不过，随着哈里斯取代拜登，泽连斯基突袭普京，一切又出现了新变化。\n据法新社、路透社爆料，14日，位于北京的高丽旅行社(Koryo\nTours)表示，关闭边境五年的朝鲜，或将在2024年底重新开放国际旅行，选择中朝边境的三池渊作为首个开放地点。\n同时，这几年来，与拜登一起构建美日韩同盟的两位好基友，岸田文雄和尹锡悦也画风突变。\n岸田文雄突然宣布放弃竞选自民党总裁，重演了他的前辈安倍的战术性退选，尹锡悦也突然放弃了连续几年的亲日言论，U转\n为大谈朝韩统一。\n而神秘的东方大国，则抓捕了跟拜登家族关系密切的基金大佬嘉实赵学军。\n正文完\n发表至： 顾子明\n2024-08-16", "content_source": "yearly_pdf", "content_chars": 1013, "fq": "A", "il": ""}